[{"entity_id": 144115188075902799,"chunk_index": 2147,"x": 14032,"z": 264,"dimension": 1},{"entity_id": 144115188075903017,"chunk_index": 2147,"x": 14084,"z": 270,"dimension": 1},{"entity_id": 144115188075900802,"chunk_index": 2146,"x": 14014,"z": 261,"dimension": 1},{"entity_id": 144115188075902539,"chunk_index": 2147,"x": 14021,"z": 252,"dimension": 1},{"entity_id": 144115188075902831,"chunk_index": 2147,"x": 14081,"z": 264,"dimension": 1},{"entity_id": 144115188075903155,"chunk_index": 2147,"x": 14028,"z": 276,"dimension": 1},{"entity_id": 144115188075902791,"chunk_index": 2147,"x": 14017,"z": 264,"dimension": 1},{"entity_id": 144115188075901022,"chunk_index": 2146,"x": 13986,"z": 276,"dimension": 1},{"entity_id": 144115188075902507,"chunk_index": 2147,"x": 14038,"z": 249,"dimension": 1},{"entity_id": 144115188075902991,"chunk_index": 2147,"x": 14045,"z": 270,"dimension": 1},{"entity_id": 144115188075903217,"chunk_index": 2147,"x": 14078,"z": 279,"dimension": 1},{"entity_id": 144115188075903323,"chunk_index": 2147,"x": 14090,"z": 282,"dimension": 1},{"entity_id": 144115188075915385,"chunk_index": 2147,"x": 14049,"z": 262,"dimension": 1},{"entity_id": 144115188075915457,"chunk_index": 2147,"x": 14045,"z": 265,"dimension": 1},{"entity_id": 144115188075903221,"chunk_index": 2147,"x": 14081,"z": 279,"dimension": 1},{"entity_id": 144115188075915265,"chunk_index": 2147,"x": 14033,"z": 259,"dimension": 1},{"entity_id": 144115188075915558,"chunk_index": 2147,"x": 14022,"z": 271,"dimension": 1},{"entity_id": 144115188075915373,"chunk_index": 2147,"x": 14021,"z": 262,"dimension": 1},{"entity_id": 144115188075915579,"chunk_index": 2147,"x": 14054,"z": 271,"dimension": 1},{"entity_id": 144115188075915552,"chunk_index": 2146,"x": 14007,"z": 271,"dimension": 1},{"entity_id": 144115188075915593,"chunk_index": 2147,"x": 14087,"z": 271,"dimension": 1},{"entity_id": 144115188075915587,"chunk_index": 2147,"x": 14073,"z": 271,"dimension": 1},{"entity_id": 144115188075915852,"chunk_index": 2147,"x": 14087,"z": 283,"dimension": 1},{"entity_id": 144115188075915854,"chunk_index": 2147,"x": 14091,"z": 283,"dimension": 1},{"entity_id": 144115188075929536,"chunk_index": 2147,"x": 14058,"z": 263,"dimension": 1},{"entity_id": 144115188075915924,"chunk_index": 2147,"x": 14078,"z": 286,"dimension": 1},{"entity_id": 144115188075915930,"chunk_index": 2147,"x": 14087,"z": 286,"dimension": 1},{"entity_id": 144115188075929254,"chunk_index": 2147,"x": 14035,"z": 251,"dimension": 1},{"entity_id": 144115188075915725,"chunk_index": 2147,"x": 14075,"z": 277,"dimension": 1},{"entity_id": 144115188075929622,"chunk_index": 2147,"x": 14087,"z": 266,"dimension": 1},{"entity_id": 144115188075929686,"chunk_index": 2147,"x": 14076,"z": 269,"dimension": 1},{"entity_id": 144115188075929756,"chunk_index": 2147,"x": 14032,"z": 272,"dimension": 1},{"entity_id": 144115188075929764,"chunk_index": 2147,"x": 14078,"z": 272,"dimension": 1},{"entity_id": 144115188075929868,"chunk_index": 2146,"x": 14002,"z": 278,"dimension": 1},{"entity_id": 144115188075929970,"chunk_index": 2147,"x": 14078,"z": 281,"dimension": 1},{"entity_id": 144115188075929828,"chunk_index": 2147,"x": 14087,"z": 275,"dimension": 1},{"entity_id": 144115188075948349,"chunk_index": 3146,"x": 13966,"z": 315,"dimension": 1},{"entity_id": 144115188075930026,"chunk_index": 2147,"x": 14077,"z": 284,"dimension": 1},{"entity_id": 144115188075948542,"chunk_index": 3146,"x": 14013,"z": 324,"dimension": 1},{"entity_id": 144115188075949481,"chunk_index": 3146,"x": 13955,"z": 366,"dimension": 1},{"entity_id": 144115188075949711,"chunk_index": 3146,"x": 14008,"z": 372,"dimension": 1},{"entity_id": 144115188075949809,"chunk_index": 3146,"x": 13996,"z": 375,"dimension": 1},{"entity_id": 144115188075949771,"chunk_index": 3146,"x": 13930,"z": 375,"dimension": 1},{"entity_id": 144115188075949669,"chunk_index": 3146,"x": 13946,"z": 372,"dimension": 1},{"entity_id": 144115188075949992,"chunk_index": 3147,"x": 14026,"z": 288,"dimension": 1},{"entity_id": 144115188075950022,"chunk_index": 3147,"x": 14088,"z": 288,"dimension": 1},{"entity_id": 144115188075949937,"chunk_index": 3146,"x": 13922,"z": 381,"dimension": 1},{"entity_id": 144115188075949943,"chunk_index": 3146,"x": 13935,"z": 381,"dimension": 1},{"entity_id": 144115188075949978,"chunk_index": 3146,"x": 14009,"z": 381,"dimension": 1},{"entity_id": 144115188075950126,"chunk_index": 3147,"x": 14085,"z": 291,"dimension": 1},{"entity_id": 144115188075950128,"chunk_index": 3147,"x": 14087,"z": 291,"dimension": 1},{"entity_id": 144115188075950266,"chunk_index": 3147,"x": 14018,"z": 297,"dimension": 1},{"entity_id": 144115188075950280,"chunk_index": 3147,"x": 14037,"z": 297,"dimension": 1},{"entity_id": 144115188075950284,"chunk_index": 3147,"x": 14047,"z": 297,"dimension": 1},{"entity_id": 144115188075950300,"chunk_index": 3147,"x": 14096,"z": 297,"dimension": 1},{"entity_id": 144115188075950418,"chunk_index": 3147,"x": 14087,"z": 300,"dimension": 1},{"entity_id": 144115188075950596,"chunk_index": 3147,"x": 14023,"z": 306,"dimension": 1},{"entity_id": 144115188075950528,"chunk_index": 3147,"x": 14092,"z": 303,"dimension": 1},{"entity_id": 144115188075950510,"chunk_index": 3147,"x": 14047,"z": 303,"dimension": 1},{"entity_id": 144115188075950692,"chunk_index": 3147,"x": 14026,"z": 309,"dimension": 1},{"entity_id": 144115188075950792,"chunk_index": 3147,"x": 14091,"z": 312,"dimension": 1},{"entity_id": 144115188075950798,"chunk_index": 3147,"x": 14097,"z": 312,"dimension": 1},{"entity_id": 144115188075950918,"chunk_index": 3147,"x": 14049,"z": 318,"dimension": 1},{"entity_id": 144115188075951219,"chunk_index": 3147,"x": 14030,"z": 330,"dimension": 1},{"entity_id": 144115188075950986,"chunk_index": 3147,"x": 14041,"z": 321,"dimension": 1},{"entity_id": 144115188075951151,"chunk_index": 3147,"x": 14072,"z": 327,"dimension": 1},{"entity_id": 144115188075950992,"chunk_index": 3147,"x": 14055,"z": 321,"dimension": 1},{"entity_id": 144115188075951253,"chunk_index": 3147,"x": 14072,"z": 330,"dimension": 1},{"entity_id": 144115188075951239,"chunk_index": 3147,"x": 14051,"z": 330,"dimension": 1},{"entity_id": 144115188075951329,"chunk_index": 3147,"x": 14016,"z": 333,"dimension": 1},{"entity_id": 144115188075951337,"chunk_index": 3147,"x": 14075,"z": 333,"dimension": 1},{"entity_id": 144115188075951387,"chunk_index": 3147,"x": 14035,"z": 336,"dimension": 1},{"entity_id": 144115188075951347,"chunk_index": 3147,"x": 14103,"z": 333,"dimension": 1},{"entity_id": 144115188075951435,"chunk_index": 3147,"x": 14071,"z": 336,"dimension": 1},{"entity_id": 144115188075951449,"chunk_index": 3147,"x": 14085,"z": 336,"dimension": 1},{"entity_id": 144115188075951677,"chunk_index": 3148,"x": 14168,"z": 345,"dimension": 1},{"entity_id": 144115188075951573,"chunk_index": 3147,"x": 14072,"z": 342,"dimension": 1},{"entity_id": 144115188075951685,"chunk_index": 3148,"x": 14184,"z": 345,"dimension": 1},{"entity_id": 144115188075951819,"chunk_index": 3148,"x": 14180,"z": 348,"dimension": 1},{"entity_id": 144115188075951821,"chunk_index": 3148,"x": 14188,"z": 348,"dimension": 1},{"entity_id": 144115188075951905,"chunk_index": 3148,"x": 14167,"z": 351,"dimension": 1},{"entity_id": 144115188075952172,"chunk_index": 3148,"x": 14187,"z": 360,"dimension": 1},{"entity_id": 144115188075952164,"chunk_index": 3148,"x": 14157,"z": 360,"dimension": 1},{"entity_id": 144115188075952174,"chunk_index": 3148,"x": 14190,"z": 360,"dimension": 1},{"entity_id": 144115188075952192,"chunk_index": 3149,"x": 14219,"z": 360,"dimension": 1},{"entity_id": 144115188075952188,"chunk_index": 3148,"x": 14205,"z": 360,"dimension": 1},{"entity_id": 144115188075952232,"chunk_index": 3147,"x": 14085,"z": 363,"dimension": 1},{"entity_id": 144115188075952288,"chunk_index": 3148,"x": 14182,"z": 363,"dimension": 1},{"entity_id": 144115188075952298,"chunk_index": 3148,"x": 14192,"z": 363,"dimension": 1},{"entity_id": 144115188075952300,"chunk_index": 3148,"x": 14195,"z": 363,"dimension": 1},{"entity_id": 144115188075952336,"chunk_index": 3147,"x": 14022,"z": 366,"dimension": 1},{"entity_id": 144115188075952368,"chunk_index": 3148,"x": 14154,"z": 366,"dimension": 1},{"entity_id": 144115188075952372,"chunk_index": 3148,"x": 14164,"z": 366,"dimension": 1},{"entity_id": 144115188075952374,"chunk_index": 3148,"x": 14168,"z": 366,"dimension": 1},{"entity_id": 144115188075952464,"chunk_index": 3148,"x": 14146,"z": 369,"dimension": 1},{"entity_id": 144115188075952588,"chunk_index": 3147,"x": 14048,"z": 372,"dimension": 1},{"entity_id": 144115188075952434,"chunk_index": 3147,"x": 14087,"z": 369,"dimension": 1},{"entity_id": 144115188075952624,"chunk_index": 3148,"x": 14158,"z": 372,"dimension": 1},{"entity_id": 144115188075952714,"chunk_index": 3147,"x": 14088,"z": 375,"dimension": 1},{"entity_id": 144115188075952912,"chunk_index": 3147,"x": 14018,"z": 381,"dimension": 1},{"entity_id": 144115188075952916,"chunk_index": 3147,"x": 14031,"z": 381,"dimension": 1},{"entity_id": 144115188075952734,"chunk_index": 3148,"x": 14124,"z": 375,"dimension": 1},{"entity_id": 144115188075952918,"chunk_index": 3147,"x": 14034,"z": 381,"dimension": 1},{"entity_id": 144115188075952924,"chunk_index": 3147,"x": 14091,"z": 381,"dimension": 1},{"entity_id": 144115188075952990,"chunk_index": 3149,"x": 14254,"z": 381,"dimension": 1},{"entity_id": 144115188075952922,"chunk_index": 3147,"x": 14086,"z": 381,"dimension": 1},{"entity_id": 144115188075953002,"chunk_index": 3149,"x": 14296,"z": 381,"dimension": 1},{"entity_id": 144115188075971616,"chunk_index": 3146,"x": 14012,"z": 292,"dimension": 1},{"entity_id": 144115188075971819,"chunk_index": 3147,"x": 14081,"z": 298,"dimension": 1},{"entity_id": 144115188075971821,"chunk_index": 3147,"x": 14095,"z": 298,"dimension": 1},{"entity_id": 144115188075971879,"chunk_index": 3147,"x": 14027,"z": 301,"dimension": 1},{"entity_id": 144115188075971895,"chunk_index": 3147,"x": 14076,"z": 301,"dimension": 1},{"entity_id": 144115188075971897,"chunk_index": 3147,"x": 14079,"z": 301,"dimension": 1},{"entity_id": 144115188075972220,"chunk_index": 3146,"x": 13971,"z": 313,"dimension": 1},{"entity_id": 144115188075972053,"chunk_index": 3147,"x": 14016,"z": 307,"dimension": 1},{"entity_id": 144115188075972059,"chunk_index": 3147,"x": 14020,"z": 307,"dimension": 1},{"entity_id": 144115188075971901,"chunk_index": 3147,"x": 14090,"z": 301,"dimension": 1},{"entity_id": 144115188075972330,"chunk_index": 3147,"x": 14030,"z": 316,"dimension": 1},{"entity_id": 144115188075972344,"chunk_index": 3147,"x": 14092,"z": 316,"dimension": 1},{"entity_id": 144115188075972410,"chunk_index": 3147,"x": 14055,"z": 319,"dimension": 1},{"entity_id": 144115188075972595,"chunk_index": 3147,"x": 14103,"z": 325,"dimension": 1},{"entity_id": 144115188075972783,"chunk_index": 3147,"x": 14037,"z": 337,"dimension": 1},{"entity_id": 144115188075972865,"chunk_index": 3147,"x": 14068,"z": 340,"dimension": 1},{"entity_id": 144115188075972961,"chunk_index": 3147,"x": 14054,"z": 346,"dimension": 1},{"entity_id": 144115188075973091,"chunk_index": 3146,"x": 14007,"z": 352,"dimension": 1},{"entity_id": 144115188075972983,"chunk_index": 3147,"x": 14105,"z": 346,"dimension": 1},{"entity_id": 144115188075973037,"chunk_index": 3147,"x": 14048,"z": 349,"dimension": 1},{"entity_id": 144115188075973107,"chunk_index": 3147,"x": 14056,"z": 352,"dimension": 1},{"entity_id": 144115188075973147,"chunk_index": 3146,"x": 13947,"z": 355,"dimension": 1},{"entity_id": 144115188075973159,"chunk_index": 3146,"x": 14009,"z": 355,"dimension": 1},{"entity_id": 144115188075973232,"chunk_index": 3147,"x": 14070,"z": 358,"dimension": 1},{"entity_id": 144115188075973304,"chunk_index": 3146,"x": 13963,"z": 361,"dimension": 1},{"entity_id": 144115188075973312,"chunk_index": 3147,"x": 14040,"z": 361,"dimension": 1},{"entity_id": 144115188075973318,"chunk_index": 3147,"x": 14064,"z": 361,"dimension": 1},{"entity_id": 144115188075973456,"chunk_index": 3147,"x": 14084,"z": 367,"dimension": 1},{"entity_id": 144115188075973350,"chunk_index": 3146,"x": 13939,"z": 364,"dimension": 1},{"entity_id": 144115188075973462,"chunk_index": 3147,"x": 14097,"z": 367,"dimension": 1},{"entity_id": 144115188075973643,"chunk_index": 3146,"x": 13952,"z": 373,"dimension": 1},{"entity_id": 144115188075973651,"chunk_index": 3146,"x": 13968,"z": 373,"dimension": 1},{"entity_id": 144115188075973723,"chunk_index": 3146,"x": 13922,"z": 376,"dimension": 1},{"entity_id": 144115188075973747,"chunk_index": 3146,"x": 14006,"z": 376,"dimension": 1},{"entity_id": 144115188075975076,"chunk_index": 3148,"x": 14170,"z": 340,"dimension": 1},{"entity_id": 144115188075975571,"chunk_index": 3148,"x": 14172,"z": 361,"dimension": 1},{"entity_id": 144115188075975398,"chunk_index": 3148,"x": 14177,"z": 355,"dimension": 1},{"entity_id": 144115188075975082,"chunk_index": 3148,"x": 14180,"z": 340,"dimension": 1},{"entity_id": 144115188075975400,"chunk_index": 3148,"x": 14178,"z": 355,"dimension": 1},{"entity_id": 144115188075975615,"chunk_index": 3148,"x": 14155,"z": 364,"dimension": 1},{"entity_id": 144115188075975726,"chunk_index": 3148,"x": 14157,"z": 367,"dimension": 1},{"entity_id": 144115188075975762,"chunk_index": 3148,"x": 14122,"z": 370,"dimension": 1},{"entity_id": 144115188075975790,"chunk_index": 3148,"x": 14190,"z": 370,"dimension": 1},{"entity_id": 144115188075975820,"chunk_index": 3150,"x": 14309,"z": 370,"dimension": 1},{"entity_id": 144115188075976067,"chunk_index": 3149,"x": 14265,"z": 379,"dimension": 1},{"entity_id": 144115188075994160,"chunk_index": 3147,"x": 14025,"z": 293,"dimension": 1},{"entity_id": 144115188075994486,"chunk_index": 3147,"x": 14039,"z": 305,"dimension": 1},{"entity_id": 144115188075994382,"chunk_index": 3146,"x": 13970,"z": 302,"dimension": 1},{"entity_id": 144115188075976115,"chunk_index": 3149,"x": 14243,"z": 382,"dimension": 1},{"entity_id": 144115188075994500,"chunk_index": 3147,"x": 14096,"z": 305,"dimension": 1},{"entity_id": 144115188075994566,"chunk_index": 3147,"x": 14096,"z": 308,"dimension": 1},{"entity_id": 144115188075994488,"chunk_index": 3147,"x": 14043,"z": 305,"dimension": 1},{"entity_id": 144115188075995019,"chunk_index": 3147,"x": 14048,"z": 326,"dimension": 1},{"entity_id": 144115188075995053,"chunk_index": 3146,"x": 13989,"z": 329,"dimension": 1},{"entity_id": 144115188075995021,"chunk_index": 3147,"x": 14051,"z": 326,"dimension": 1},{"entity_id": 144115188075995307,"chunk_index": 3147,"x": 14034,"z": 341,"dimension": 1},{"entity_id": 144115188075995371,"chunk_index": 3147,"x": 14056,"z": 344,"dimension": 1},{"entity_id": 144115188075995379,"chunk_index": 3147,"x": 14067,"z": 344,"dimension": 1},{"entity_id": 144115188075995437,"chunk_index": 3148,"x": 14174,"z": 347,"dimension": 1},{"entity_id": 144115188075995503,"chunk_index": 3148,"x": 14182,"z": 350,"dimension": 1},{"entity_id": 144115188075995439,"chunk_index": 3148,"x": 14181,"z": 347,"dimension": 1},{"entity_id": 144115188075995586,"chunk_index": 3148,"x": 14174,"z": 353,"dimension": 1},{"entity_id": 144115188075995712,"chunk_index": 3148,"x": 14185,"z": 356,"dimension": 1},{"entity_id": 144115188075995649,"chunk_index": 3146,"x": 13969,"z": 356,"dimension": 1},{"entity_id": 144115188075995837,"chunk_index": 3146,"x": 14000,"z": 362,"dimension": 1},{"entity_id": 144115188075995665,"chunk_index": 3147,"x": 14064,"z": 356,"dimension": 1},{"entity_id": 144115188075995819,"chunk_index": 3148,"x": 14160,"z": 359,"dimension": 1},{"entity_id": 144115188075995714,"chunk_index": 3148,"x": 14186,"z": 356,"dimension": 1},{"entity_id": 144115188075995877,"chunk_index": 3148,"x": 14123,"z": 362,"dimension": 1},{"entity_id": 144115188075995980,"chunk_index": 3148,"x": 14147,"z": 365,"dimension": 1},{"entity_id": 144115188075995887,"chunk_index": 3148,"x": 14158,"z": 362,"dimension": 1},{"entity_id": 144115188075996000,"chunk_index": 3146,"x": 13928,"z": 368,"dimension": 1},{"entity_id": 144115188075996024,"chunk_index": 3146,"x": 13990,"z": 368,"dimension": 1},{"entity_id": 144115188075996028,"chunk_index": 3146,"x": 14001,"z": 368,"dimension": 1},{"entity_id": 144115188075996191,"chunk_index": 3148,"x": 14154,"z": 371,"dimension": 1},{"entity_id": 144115188075996271,"chunk_index": 3148,"x": 14124,"z": 374,"dimension": 1},{"entity_id": 144115188075996247,"chunk_index": 3146,"x": 14015,"z": 374,"dimension": 1},{"entity_id": 144115188075996034,"chunk_index": 3147,"x": 14033,"z": 368,"dimension": 1},{"entity_id": 144115188075996209,"chunk_index": 3146,"x": 13930,"z": 374,"dimension": 1},{"entity_id": 144115188075996434,"chunk_index": 3146,"x": 13987,"z": 380,"dimension": 1},{"entity_id": 144115188075996406,"chunk_index": 3148,"x": 14162,"z": 377,"dimension": 1},{"entity_id": 144115188075996472,"chunk_index": 3147,"x": 14099,"z": 380,"dimension": 1},{"entity_id": 144115188075996633,"chunk_index": 4148,"x": 14194,"z": 383,"dimension": 1},{"entity_id": 144115188075996635,"chunk_index": 4148,"x": 14201,"z": 383,"dimension": 1},{"entity_id": 144115188075998509,"chunk_index": 3149,"x": 14263,"z": 380,"dimension": 1},{"entity_id": 144115188075998199,"chunk_index": 3149,"x": 14240,"z": 365,"dimension": 1},{"entity_id": 144115188076018632,"chunk_index": 4146,"x": 14007,"z": 387,"dimension": 1},{"entity_id": 144115188075998297,"chunk_index": 3149,"x": 14237,"z": 371,"dimension": 1},{"entity_id": 144115188075998311,"chunk_index": 3149,"x": 14265,"z": 371,"dimension": 1},{"entity_id": 144115188076018686,"chunk_index": 4146,"x": 13970,"z": 390,"dimension": 1},{"entity_id": 144115188076018688,"chunk_index": 4146,"x": 13978,"z": 390,"dimension": 1},{"entity_id": 144115188076018786,"chunk_index": 4146,"x": 13920,"z": 396,"dimension": 1},{"entity_id": 144115188076018864,"chunk_index": 4146,"x": 13964,"z": 399,"dimension": 1},{"entity_id": 144115188076019105,"chunk_index": 4146,"x": 14012,"z": 408,"dimension": 1},{"entity_id": 144115188076019169,"chunk_index": 4146,"x": 13973,"z": 411,"dimension": 1},{"entity_id": 144115188076019325,"chunk_index": 4146,"x": 13940,"z": 417,"dimension": 1},{"entity_id": 144115188076019183,"chunk_index": 4146,"x": 14002,"z": 411,"dimension": 1},{"entity_id": 144115188076019175,"chunk_index": 4146,"x": 13987,"z": 411,"dimension": 1},{"entity_id": 144115188076019249,"chunk_index": 4146,"x": 13952,"z": 414,"dimension": 1},{"entity_id": 144115188076019337,"chunk_index": 4146,"x": 13961,"z": 417,"dimension": 1},{"entity_id": 144115188076019435,"chunk_index": 4146,"x": 13944,"z": 420,"dimension": 1},{"entity_id": 144115188076019443,"chunk_index": 4146,"x": 13953,"z": 420,"dimension": 1},{"entity_id": 144115188076019445,"chunk_index": 4146,"x": 13954,"z": 420,"dimension": 1},{"entity_id": 144115188076019451,"chunk_index": 4146,"x": 13958,"z": 420,"dimension": 1},{"entity_id": 144115188076019509,"chunk_index": 4146,"x": 13941,"z": 423,"dimension": 1},{"entity_id": 144115188076019519,"chunk_index": 4146,"x": 13963,"z": 423,"dimension": 1},{"entity_id": 144115188076019527,"chunk_index": 4146,"x": 13987,"z": 423,"dimension": 1},{"entity_id": 144115188076019670,"chunk_index": 4145,"x": 13889,"z": 429,"dimension": 1},{"entity_id": 144115188076019672,"chunk_index": 4145,"x": 13893,"z": 429,"dimension": 1},{"entity_id": 144115188076019700,"chunk_index": 4146,"x": 13948,"z": 429,"dimension": 1},{"entity_id": 144115188076019680,"chunk_index": 4145,"x": 13915,"z": 429,"dimension": 1},{"entity_id": 144115188076019710,"chunk_index": 4146,"x": 13966,"z": 429,"dimension": 1},{"entity_id": 144115188076019748,"chunk_index": 4145,"x": 13905,"z": 432,"dimension": 1},{"entity_id": 144115188076019860,"chunk_index": 4145,"x": 13919,"z": 435,"dimension": 1},{"entity_id": 144115188076019874,"chunk_index": 4146,"x": 13951,"z": 435,"dimension": 1},{"entity_id": 144115188076019892,"chunk_index": 4146,"x": 13970,"z": 435,"dimension": 1},{"entity_id": 144115188076020062,"chunk_index": 4145,"x": 13882,"z": 441,"dimension": 1},{"entity_id": 144115188076020068,"chunk_index": 4146,"x": 13937,"z": 441,"dimension": 1},{"entity_id": 144115188076020086,"chunk_index": 4146,"x": 13972,"z": 441,"dimension": 1},{"entity_id": 144115188076020074,"chunk_index": 4146,"x": 13956,"z": 441,"dimension": 1},{"entity_id": 144115188076020096,"chunk_index": 4146,"x": 13999,"z": 441,"dimension": 1},{"entity_id": 144115188076020140,"chunk_index": 4146,"x": 13942,"z": 444,"dimension": 1},{"entity_id": 144115188076020263,"chunk_index": 4146,"x": 13942,"z": 447,"dimension": 1},{"entity_id": 144115188076020148,"chunk_index": 4146,"x": 13960,"z": 444,"dimension": 1},{"entity_id": 144115188076020100,"chunk_index": 4146,"x": 14002,"z": 441,"dimension": 1},{"entity_id": 144115188076020367,"chunk_index": 4146,"x": 13966,"z": 450,"dimension": 1},{"entity_id": 144115188076020353,"chunk_index": 4146,"x": 13952,"z": 450,"dimension": 1},{"entity_id": 144115188076020351,"chunk_index": 4146,"x": 13950,"z": 450,"dimension": 1},{"entity_id": 144115188076020373,"chunk_index": 4146,"x": 13979,"z": 450,"dimension": 1},{"entity_id": 144115188076020466,"chunk_index": 4146,"x": 13936,"z": 453,"dimension": 1},{"entity_id": 144115188076020492,"chunk_index": 4146,"x": 13982,"z": 453,"dimension": 1},{"entity_id": 144115188076021007,"chunk_index": 4146,"x": 13993,"z": 468,"dimension": 1},{"entity_id": 144115188076020825,"chunk_index": 4146,"x": 13981,"z": 462,"dimension": 1},{"entity_id": 144115188076020823,"chunk_index": 4146,"x": 13978,"z": 462,"dimension": 1},{"entity_id": 144115188076020623,"chunk_index": 4146,"x": 14005,"z": 456,"dimension": 1},{"entity_id": 144115188076021103,"chunk_index": 4146,"x": 14005,"z": 471,"dimension": 1},{"entity_id": 144115188076021093,"chunk_index": 4146,"x": 13984,"z": 471,"dimension": 1},{"entity_id": 144115188076021197,"chunk_index": 4146,"x": 14012,"z": 474,"dimension": 1},{"entity_id": 144115188076021195,"chunk_index": 4146,"x": 14011,"z": 474,"dimension": 1},{"entity_id": 144115188076021255,"chunk_index": 4145,"x": 13895,"z": 477,"dimension": 1},{"entity_id": 144115188076021283,"chunk_index": 4146,"x": 14014,"z": 477,"dimension": 1},{"entity_id": 144115188076021295,"chunk_index": 4147,"x": 14039,"z": 384,"dimension": 1},{"entity_id": 144115188076021423,"chunk_index": 4147,"x": 14087,"z": 387,"dimension": 1},{"entity_id": 144115188076021421,"chunk_index": 4147,"x": 14086,"z": 387,"dimension": 1},{"entity_id": 144115188076021343,"chunk_index": 4148,"x": 14201,"z": 384,"dimension": 1},{"entity_id": 144115188076021557,"chunk_index": 4147,"x": 14082,"z": 390,"dimension": 1},{"entity_id": 144115188076021573,"chunk_index": 4148,"x": 14137,"z": 390,"dimension": 1},{"entity_id": 144115188076021445,"chunk_index": 4148,"x": 14143,"z": 387,"dimension": 1},{"entity_id": 144115188076021609,"chunk_index": 4147,"x": 14026,"z": 393,"dimension": 1},{"entity_id": 144115188076021705,"chunk_index": 4147,"x": 14052,"z": 396,"dimension": 1},{"entity_id": 144115188076021713,"chunk_index": 4147,"x": 14084,"z": 396,"dimension": 1},{"entity_id": 144115188076021715,"chunk_index": 4147,"x": 14087,"z": 396,"dimension": 1},{"entity_id": 144115188076021734,"chunk_index": 4148,"x": 14117,"z": 396,"dimension": 1},{"entity_id": 144115188076021877,"chunk_index": 4147,"x": 14104,"z": 399,"dimension": 1},{"entity_id": 144115188076021758,"chunk_index": 4148,"x": 14148,"z": 396,"dimension": 1},{"entity_id": 144115188076021898,"chunk_index": 4148,"x": 14123,"z": 399,"dimension": 1},{"entity_id": 144115188076021956,"chunk_index": 4147,"x": 14030,"z": 402,"dimension": 1},{"entity_id": 144115188076021984,"chunk_index": 4147,"x": 14061,"z": 402,"dimension": 1},{"entity_id": 144115188076021992,"chunk_index": 4147,"x": 14082,"z": 402,"dimension": 1},{"entity_id": 144115188076022002,"chunk_index": 4147,"x": 14097,"z": 402,"dimension": 1},{"entity_id": 144115188076022065,"chunk_index": 4149,"x": 14293,"z": 402,"dimension": 1},{"entity_id": 144115188076022358,"chunk_index": 4149,"x": 14231,"z": 411,"dimension": 1},{"entity_id": 144115188076022382,"chunk_index": 4147,"x": 14041,"z": 414,"dimension": 1},{"entity_id": 144115188076022410,"chunk_index": 4147,"x": 14104,"z": 414,"dimension": 1},{"entity_id": 144115188076022579,"chunk_index": 4148,"x": 14151,"z": 417,"dimension": 1},{"entity_id": 144115188076022412,"chunk_index": 4147,"x": 14109,"z": 414,"dimension": 1},{"entity_id": 144115188076022595,"chunk_index": 4148,"x": 14201,"z": 417,"dimension": 1},{"entity_id": 144115188076022587,"chunk_index": 4148,"x": 14180,"z": 417,"dimension": 1},{"entity_id": 144115188076022671,"chunk_index": 4147,"x": 14088,"z": 420,"dimension": 1},{"entity_id": 144115188076022768,"chunk_index": 4147,"x": 14059,"z": 423,"dimension": 1},{"entity_id": 144115188076022786,"chunk_index": 4148,"x": 14113,"z": 423,"dimension": 1},{"entity_id": 144115188076022810,"chunk_index": 4148,"x": 14175,"z": 423,"dimension": 1},{"entity_id": 144115188076022918,"chunk_index": 4148,"x": 14121,"z": 426,"dimension": 1},{"entity_id": 144115188076022960,"chunk_index": 4149,"x": 14230,"z": 426,"dimension": 1},{"entity_id": 144115188076022814,"chunk_index": 4148,"x": 14193,"z": 423,"dimension": 1},{"entity_id": 144115188076023037,"chunk_index": 4147,"x": 14107,"z": 429,"dimension": 1},{"entity_id": 144115188076023184,"chunk_index": 4147,"x": 14105,"z": 432,"dimension": 1},{"entity_id": 144115188076023051,"chunk_index": 4148,"x": 14130,"z": 429,"dimension": 1},{"entity_id": 144115188076023216,"chunk_index": 4148,"x": 14191,"z": 432,"dimension": 1},{"entity_id": 144115188076022988,"chunk_index": 4149,"x": 14300,"z": 426,"dimension": 1},{"entity_id": 144115188076023234,"chunk_index": 4149,"x": 14228,"z": 432,"dimension": 1},{"entity_id": 144115188076023460,"chunk_index": 4148,"x": 14171,"z": 438,"dimension": 1},{"entity_id": 144115188076023314,"chunk_index": 4147,"x": 14108,"z": 435,"dimension": 1},{"entity_id": 144115188076023486,"chunk_index": 4148,"x": 14204,"z": 438,"dimension": 1},{"entity_id": 144115188076023288,"chunk_index": 4147,"x": 14038,"z": 435,"dimension": 1},{"entity_id": 144115188076023566,"chunk_index": 4148,"x": 14124,"z": 441,"dimension": 1},{"entity_id": 144115188076023512,"chunk_index": 4147,"x": 14023,"z": 441,"dimension": 1},{"entity_id": 144115188076023532,"chunk_index": 4147,"x": 14101,"z": 441,"dimension": 1},{"entity_id": 144115188076023584,"chunk_index": 4148,"x": 14142,"z": 441,"dimension": 1},{"entity_id": 144115188076023588,"chunk_index": 4148,"x": 14147,"z": 441,"dimension": 1},{"entity_id": 144115188076023687,"chunk_index": 4148,"x": 14147,"z": 444,"dimension": 1},{"entity_id": 144115188076023767,"chunk_index": 4147,"x": 14071,"z": 447,"dimension": 1},{"entity_id": 144115188076023837,"chunk_index": 4148,"x": 14172,"z": 447,"dimension": 1},{"entity_id": 144115188076023973,"chunk_index": 4148,"x": 14180,"z": 450,"dimension": 1},{"entity_id": 144115188076023855,"chunk_index": 4148,"x": 14202,"z": 447,"dimension": 1},{"entity_id": 144115188076023875,"chunk_index": 4149,"x": 14264,"z": 447,"dimension": 1},{"entity_id": 144115188076023921,"chunk_index": 4147,"x": 14093,"z": 450,"dimension": 1},{"entity_id": 144115188076023979,"chunk_index": 4148,"x": 14193,"z": 450,"dimension": 1},{"entity_id": 144115188076023977,"chunk_index": 4148,"x": 14192,"z": 450,"dimension": 1},{"entity_id": 144115188076023981,"chunk_index": 4148,"x": 14194,"z": 450,"dimension": 1},{"entity_id": 144115188076024072,"chunk_index": 4148,"x": 14152,"z": 453,"dimension": 1},{"entity_id": 144115188076024094,"chunk_index": 4149,"x": 14221,"z": 453,"dimension": 1},{"entity_id": 144115188076024134,"chunk_index": 4149,"x": 14285,"z": 453,"dimension": 1},{"entity_id": 144115188076024174,"chunk_index": 4147,"x": 14071,"z": 456,"dimension": 1},{"entity_id": 144115188076024154,"chunk_index": 4147,"x": 14038,"z": 456,"dimension": 1},{"entity_id": 144115188076024176,"chunk_index": 4147,"x": 14080,"z": 456,"dimension": 1},{"entity_id": 144115188076024230,"chunk_index": 4148,"x": 14190,"z": 456,"dimension": 1},{"entity_id": 144115188076024192,"chunk_index": 4147,"x": 14110,"z": 456,"dimension": 1},{"entity_id": 144115188076024208,"chunk_index": 4148,"x": 14135,"z": 456,"dimension": 1},{"entity_id": 144115188076024216,"chunk_index": 4148,"x": 14152,"z": 456,"dimension": 1},{"entity_id": 144115188076024286,"chunk_index": 4149,"x": 14300,"z": 456,"dimension": 1},{"entity_id": 144115188076024322,"chunk_index": 4147,"x": 14071,"z": 459,"dimension": 1},{"entity_id": 144115188076024366,"chunk_index": 4148,"x": 14147,"z": 459,"dimension": 1},{"entity_id": 144115188076024392,"chunk_index": 4149,"x": 14208,"z": 459,"dimension": 1},{"entity_id": 144115188076024479,"chunk_index": 4147,"x": 14061,"z": 462,"dimension": 1},{"entity_id": 144115188076024507,"chunk_index": 4148,"x": 14152,"z": 462,"dimension": 1},{"entity_id": 144115188076024777,"chunk_index": 4148,"x": 14196,"z": 468,"dimension": 1},{"entity_id": 144115188076024799,"chunk_index": 4149,"x": 14245,"z": 468,"dimension": 1},{"entity_id": 144115188076024847,"chunk_index": 4147,"x": 14058,"z": 471,"dimension": 1},{"entity_id": 144115188076024646,"chunk_index": 4148,"x": 14175,"z": 465,"dimension": 1},{"entity_id": 144115188076024938,"chunk_index": 4148,"x": 14150,"z": 471,"dimension": 1},{"entity_id": 144115188076024952,"chunk_index": 4148,"x": 14191,"z": 471,"dimension": 1},{"entity_id": 144115188076024966,"chunk_index": 4149,"x": 14214,"z": 471,"dimension": 1},{"entity_id": 144115188076024994,"chunk_index": 4149,"x": 14299,"z": 471,"dimension": 1},{"entity_id": 144115188076025088,"chunk_index": 4148,"x": 14173,"z": 474,"dimension": 1},{"entity_id": 144115188076025096,"chunk_index": 4148,"x": 14187,"z": 474,"dimension": 1},{"entity_id": 144115188076025231,"chunk_index": 4148,"x": 14192,"z": 477,"dimension": 1},{"entity_id": 144115188076025107,"chunk_index": 4149,"x": 14210,"z": 474,"dimension": 1},{"entity_id": 144115188076025092,"chunk_index": 4148,"x": 14181,"z": 474,"dimension": 1},{"entity_id": 144115188076025233,"chunk_index": 4148,"x": 14195,"z": 477,"dimension": 1},{"entity_id": 144115188076026137,"chunk_index": 4150,"x": 14358,"z": 414,"dimension": 1},{"entity_id": 144115188076025581,"chunk_index": 4150,"x": 14312,"z": 396,"dimension": 1},{"entity_id": 144115188076026203,"chunk_index": 4150,"x": 14332,"z": 417,"dimension": 1},{"entity_id": 144115188076026139,"chunk_index": 4150,"x": 14360,"z": 414,"dimension": 1},{"entity_id": 144115188076026322,"chunk_index": 4150,"x": 14360,"z": 420,"dimension": 1},{"entity_id": 144115188076026485,"chunk_index": 4152,"x": 14534,"z": 423,"dimension": 1},{"entity_id": 144115188076026326,"chunk_index": 4150,"x": 14364,"z": 420,"dimension": 1},{"entity_id": 144115188076026394,"chunk_index": 4150,"x": 14309,"z": 423,"dimension": 1},{"entity_id": 144115188076026415,"chunk_index": 4150,"x": 14340,"z": 423,"dimension": 1},{"entity_id": 144115188076026503,"chunk_index": 4150,"x": 14334,"z": 426,"dimension": 1},{"entity_id": 144115188076026505,"chunk_index": 4150,"x": 14346,"z": 426,"dimension": 1},{"entity_id": 144115188076026575,"chunk_index": 4150,"x": 14338,"z": 429,"dimension": 1},{"entity_id": 144115188076026644,"chunk_index": 4150,"x": 14347,"z": 432,"dimension": 1},{"entity_id": 144115188076026646,"chunk_index": 4150,"x": 14348,"z": 432,"dimension": 1},{"entity_id": 144115188076026650,"chunk_index": 4150,"x": 14357,"z": 432,"dimension": 1},{"entity_id": 144115188076026744,"chunk_index": 4150,"x": 14356,"z": 435,"dimension": 1},{"entity_id": 144115188076026816,"chunk_index": 4150,"x": 14313,"z": 438,"dimension": 1},{"entity_id": 144115188076026692,"chunk_index": 4152,"x": 14530,"z": 432,"dimension": 1},{"entity_id": 144115188076026734,"chunk_index": 4150,"x": 14331,"z": 435,"dimension": 1},{"entity_id": 144115188076026818,"chunk_index": 4150,"x": 14320,"z": 438,"dimension": 1},{"entity_id": 144115188076026824,"chunk_index": 4150,"x": 14338,"z": 438,"dimension": 1},{"entity_id": 144115188076026830,"chunk_index": 4150,"x": 14342,"z": 438,"dimension": 1},{"entity_id": 144115188076026866,"chunk_index": 4150,"x": 14316,"z": 441,"dimension": 1},{"entity_id": 144115188076026864,"chunk_index": 4150,"x": 14311,"z": 441,"dimension": 1},{"entity_id": 144115188076026942,"chunk_index": 4150,"x": 14305,"z": 444,"dimension": 1},{"entity_id": 144115188076026868,"chunk_index": 4150,"x": 14321,"z": 441,"dimension": 1},{"entity_id": 144115188076026880,"chunk_index": 4150,"x": 14337,"z": 441,"dimension": 1},{"entity_id": 144115188076027034,"chunk_index": 4150,"x": 14318,"z": 447,"dimension": 1},{"entity_id": 144115188076027042,"chunk_index": 4150,"x": 14345,"z": 447,"dimension": 1},{"entity_id": 144115188076027096,"chunk_index": 4152,"x": 14544,"z": 447,"dimension": 1},{"entity_id": 144115188076027126,"chunk_index": 4150,"x": 14335,"z": 450,"dimension": 1},{"entity_id": 144115188076027187,"chunk_index": 4152,"x": 14552,"z": 450,"dimension": 1},{"entity_id": 144115188076027177,"chunk_index": 4152,"x": 14526,"z": 450,"dimension": 1},{"entity_id": 144115188076027215,"chunk_index": 4150,"x": 14339,"z": 453,"dimension": 1},{"entity_id": 144115188076027382,"chunk_index": 4150,"x": 14324,"z": 459,"dimension": 1},{"entity_id": 144115188076027348,"chunk_index": 4151,"x": 14483,"z": 456,"dimension": 1},{"entity_id": 144115188076027462,"chunk_index": 4152,"x": 14536,"z": 459,"dimension": 1},{"entity_id": 144115188076027488,"chunk_index": 4150,"x": 14311,"z": 462,"dimension": 1},{"entity_id": 144115188076027498,"chunk_index": 4150,"x": 14341,"z": 462,"dimension": 1},{"entity_id": 144115188076027500,"chunk_index": 4150,"x": 14346,"z": 462,"dimension": 1},{"entity_id": 144115188076027589,"chunk_index": 4150,"x": 14316,"z": 465,"dimension": 1},{"entity_id": 144115188076027595,"chunk_index": 4150,"x": 14333,"z": 465,"dimension": 1},{"entity_id": 144115188076027591,"chunk_index": 4150,"x": 14319,"z": 465,"dimension": 1},{"entity_id": 144115188076027641,"chunk_index": 4151,"x": 14467,"z": 465,"dimension": 1},{"entity_id": 144115188076027603,"chunk_index": 4150,"x": 14345,"z": 465,"dimension": 1},{"entity_id": 144115188076027702,"chunk_index": 4152,"x": 14555,"z": 465,"dimension": 1},{"entity_id": 144115188076027661,"chunk_index": 4151,"x": 14487,"z": 465,"dimension": 1},{"entity_id": 144115188076027704,"chunk_index": 4152,"x": 14558,"z": 465,"dimension": 1},{"entity_id": 144115188076027728,"chunk_index": 4150,"x": 14326,"z": 468,"dimension": 1},{"entity_id": 144115188076027756,"chunk_index": 4151,"x": 14462,"z": 468,"dimension": 1},{"entity_id": 144115188076027777,"chunk_index": 4152,"x": 14511,"z": 468,"dimension": 1},{"entity_id": 144115188076027760,"chunk_index": 4151,"x": 14468,"z": 468,"dimension": 1},{"entity_id": 144115188076027829,"chunk_index": 4150,"x": 14342,"z": 471,"dimension": 1},{"entity_id": 144115188076027970,"chunk_index": 4152,"x": 14546,"z": 474,"dimension": 1},{"entity_id": 144115188076028105,"chunk_index": 4152,"x": 14526,"z": 477,"dimension": 1},{"entity_id": 144115188076028014,"chunk_index": 4152,"x": 14587,"z": 474,"dimension": 1},{"entity_id": 144115188076027879,"chunk_index": 4152,"x": 14539,"z": 471,"dimension": 1},{"entity_id": 144115188076047826,"chunk_index": 4146,"x": 14006,"z": 385,"dimension": 1},{"entity_id": 144115188076047854,"chunk_index": 4147,"x": 14099,"z": 385,"dimension": 1},{"entity_id": 144115188076047937,"chunk_index": 4146,"x": 14008,"z": 388,"dimension": 1},{"entity_id": 144115188076047947,"chunk_index": 4147,"x": 14030,"z": 388,"dimension": 1},{"entity_id": 144115188076047949,"chunk_index": 4147,"x": 14031,"z": 388,"dimension": 1},{"entity_id": 144115188076047931,"chunk_index": 4146,"x": 13994,"z": 388,"dimension": 1},{"entity_id": 144115188076048113,"chunk_index": 4147,"x": 14103,"z": 391,"dimension": 1},{"entity_id": 144115188076047989,"chunk_index": 4147,"x": 14101,"z": 388,"dimension": 1},{"entity_id": 144115188076048175,"chunk_index": 4147,"x": 14030,"z": 394,"dimension": 1},{"entity_id": 144115188076048165,"chunk_index": 4146,"x": 13995,"z": 394,"dimension": 1},{"entity_id": 144115188076048187,"chunk_index": 4147,"x": 14089,"z": 394,"dimension": 1},{"entity_id": 144115188076048195,"chunk_index": 4147,"x": 14109,"z": 394,"dimension": 1},{"entity_id": 144115188076048237,"chunk_index": 4147,"x": 14015,"z": 397,"dimension": 1},{"entity_id": 144115188076048247,"chunk_index": 4147,"x": 14054,"z": 397,"dimension": 1},{"entity_id": 144115188076048301,"chunk_index": 4146,"x": 13957,"z": 400,"dimension": 1},{"entity_id": 144115188076048305,"chunk_index": 4146,"x": 13985,"z": 400,"dimension": 1},{"entity_id": 144115188076048307,"chunk_index": 4146,"x": 13986,"z": 400,"dimension": 1},{"entity_id": 144115188076048315,"chunk_index": 4146,"x": 14000,"z": 400,"dimension": 1},{"entity_id": 144115188076048347,"chunk_index": 4147,"x": 14104,"z": 400,"dimension": 1},{"entity_id": 144115188076048408,"chunk_index": 4146,"x": 13955,"z": 403,"dimension": 1},{"entity_id": 144115188076048410,"chunk_index": 4146,"x": 13966,"z": 403,"dimension": 1},{"entity_id": 144115188076048473,"chunk_index": 4147,"x": 14051,"z": 403,"dimension": 1},{"entity_id": 144115188076048416,"chunk_index": 4146,"x": 13985,"z": 403,"dimension": 1},{"entity_id": 144115188076048622,"chunk_index": 4146,"x": 13986,"z": 406,"dimension": 1},{"entity_id": 144115188076048640,"chunk_index": 4147,"x": 14078,"z": 406,"dimension": 1},{"entity_id": 144115188076048634,"chunk_index": 4147,"x": 14054,"z": 406,"dimension": 1},{"entity_id": 144115188076048475,"chunk_index": 4147,"x": 14060,"z": 403,"dimension": 1},{"entity_id": 144115188076048660,"chunk_index": 4147,"x": 14099,"z": 406,"dimension": 1},{"entity_id": 144115188076048680,"chunk_index": 4146,"x": 13947,"z": 409,"dimension": 1},{"entity_id": 144115188076048702,"chunk_index": 4146,"x": 13993,"z": 409,"dimension": 1},{"entity_id": 144115188076048704,"chunk_index": 4146,"x": 13998,"z": 409,"dimension": 1},{"entity_id": 144115188076048706,"chunk_index": 4146,"x": 14000,"z": 409,"dimension": 1},{"entity_id": 144115188076048794,"chunk_index": 4146,"x": 14002,"z": 412,"dimension": 1},{"entity_id": 144115188076048846,"chunk_index": 4146,"x": 13934,"z": 415,"dimension": 1},{"entity_id": 144115188076048968,"chunk_index": 4146,"x": 13994,"z": 418,"dimension": 1},{"entity_id": 144115188076048940,"chunk_index": 4145,"x": 13914,"z": 418,"dimension": 1},{"entity_id": 144115188076049038,"chunk_index": 4146,"x": 13977,"z": 421,"dimension": 1},{"entity_id": 144115188076049095,"chunk_index": 4147,"x": 14045,"z": 421,"dimension": 1},{"entity_id": 144115188076049205,"chunk_index": 4145,"x": 13906,"z": 427,"dimension": 1},{"entity_id": 144115188076049159,"chunk_index": 4146,"x": 13960,"z": 424,"dimension": 1},{"entity_id": 144115188076049310,"chunk_index": 4145,"x": 13910,"z": 430,"dimension": 1},{"entity_id": 144115188076049302,"chunk_index": 4145,"x": 13898,"z": 430,"dimension": 1},{"entity_id": 144115188076049395,"chunk_index": 4147,"x": 14065,"z": 430,"dimension": 1},{"entity_id": 144115188076049389,"chunk_index": 4147,"x": 14059,"z": 430,"dimension": 1},{"entity_id": 144115188076049453,"chunk_index": 4146,"x": 13967,"z": 433,"dimension": 1},{"entity_id": 144115188076049455,"chunk_index": 4146,"x": 13979,"z": 433,"dimension": 1},{"entity_id": 144115188076049433,"chunk_index": 4145,"x": 13917,"z": 433,"dimension": 1},{"entity_id": 144115188076049447,"chunk_index": 4146,"x": 13948,"z": 433,"dimension": 1},{"entity_id": 144115188076049619,"chunk_index": 4146,"x": 13953,"z": 439,"dimension": 1},{"entity_id": 144115188076049617,"chunk_index": 4146,"x": 13950,"z": 439,"dimension": 1},{"entity_id": 144115188076049527,"chunk_index": 4146,"x": 13969,"z": 436,"dimension": 1},{"entity_id": 144115188076049519,"chunk_index": 4146,"x": 13953,"z": 436,"dimension": 1},{"entity_id": 144115188076049737,"chunk_index": 4146,"x": 13976,"z": 442,"dimension": 1},{"entity_id": 144115188076049860,"chunk_index": 4147,"x": 14015,"z": 445,"dimension": 1},{"entity_id": 144115188076049956,"chunk_index": 4146,"x": 13973,"z": 448,"dimension": 1},{"entity_id": 144115188076049960,"chunk_index": 4146,"x": 13976,"z": 448,"dimension": 1},{"entity_id": 144115188076050023,"chunk_index": 4147,"x": 14068,"z": 448,"dimension": 1},{"entity_id": 144115188076050112,"chunk_index": 4147,"x": 14078,"z": 451,"dimension": 1},{"entity_id": 144115188076050172,"chunk_index": 4146,"x": 13957,"z": 454,"dimension": 1},{"entity_id": 144115188076050116,"chunk_index": 4147,"x": 14089,"z": 451,"dimension": 1},{"entity_id": 144115188076050168,"chunk_index": 4146,"x": 13953,"z": 454,"dimension": 1},{"entity_id": 144115188076050180,"chunk_index": 4146,"x": 13976,"z": 454,"dimension": 1},{"entity_id": 144115188076050222,"chunk_index": 4147,"x": 14084,"z": 454,"dimension": 1},{"entity_id": 144115188076050226,"chunk_index": 4147,"x": 14105,"z": 454,"dimension": 1},{"entity_id": 144115188076050322,"chunk_index": 4147,"x": 14075,"z": 457,"dimension": 1},{"entity_id": 144115188076050330,"chunk_index": 4147,"x": 14101,"z": 457,"dimension": 1},{"entity_id": 144115188076050270,"chunk_index": 4146,"x": 13955,"z": 457,"dimension": 1},{"entity_id": 144115188076050386,"chunk_index": 4146,"x": 13971,"z": 460,"dimension": 1},{"entity_id": 144115188076050394,"chunk_index": 4146,"x": 13982,"z": 460,"dimension": 1},{"entity_id": 144115188076050510,"chunk_index": 4147,"x": 14054,"z": 463,"dimension": 1},{"entity_id": 144115188076050478,"chunk_index": 4146,"x": 13973,"z": 463,"dimension": 1},{"entity_id": 144115188076050396,"chunk_index": 4146,"x": 13993,"z": 460,"dimension": 1},{"entity_id": 144115188076050536,"chunk_index": 4147,"x": 14103,"z": 463,"dimension": 1},{"entity_id": 144115188076050606,"chunk_index": 4147,"x": 14020,"z": 466,"dimension": 1},{"entity_id": 144115188076050574,"chunk_index": 4146,"x": 13988,"z": 466,"dimension": 1},{"entity_id": 144115188076050572,"chunk_index": 4146,"x": 13982,"z": 466,"dimension": 1},{"entity_id": 144115188076050679,"chunk_index": 4147,"x": 14020,"z": 469,"dimension": 1},{"entity_id": 144115188076050759,"chunk_index": 4145,"x": 13903,"z": 472,"dimension": 1},{"entity_id": 144115188076050616,"chunk_index": 4147,"x": 14102,"z": 466,"dimension": 1},{"entity_id": 144115188076050909,"chunk_index": 4145,"x": 13895,"z": 478,"dimension": 1},{"entity_id": 144115188076050873,"chunk_index": 4147,"x": 14035,"z": 475,"dimension": 1},{"entity_id": 144115188076050847,"chunk_index": 4145,"x": 13901,"z": 475,"dimension": 1},{"entity_id": 144115188076051099,"chunk_index": 4148,"x": 14196,"z": 385,"dimension": 1},{"entity_id": 144115188076051081,"chunk_index": 4148,"x": 14142,"z": 385,"dimension": 1},{"entity_id": 144115188076051343,"chunk_index": 4150,"x": 14312,"z": 394,"dimension": 1},{"entity_id": 144115188076051567,"chunk_index": 4149,"x": 14300,"z": 403,"dimension": 1},{"entity_id": 144115188076051721,"chunk_index": 4149,"x": 14218,"z": 409,"dimension": 1},{"entity_id": 144115188076051743,"chunk_index": 4150,"x": 14319,"z": 409,"dimension": 1},{"entity_id": 144115188076051723,"chunk_index": 4149,"x": 14219,"z": 409,"dimension": 1},{"entity_id": 144115188076051857,"chunk_index": 4150,"x": 14354,"z": 412,"dimension": 1},{"entity_id": 144115188076051931,"chunk_index": 4150,"x": 14351,"z": 415,"dimension": 1},{"entity_id": 144115188076051975,"chunk_index": 4149,"x": 14233,"z": 418,"dimension": 1},{"entity_id": 144115188076052195,"chunk_index": 4148,"x": 14122,"z": 424,"dimension": 1},{"entity_id": 144115188076052233,"chunk_index": 4148,"x": 14197,"z": 424,"dimension": 1},{"entity_id": 144115188076051991,"chunk_index": 4150,"x": 14321,"z": 418,"dimension": 1},{"entity_id": 144115188076052133,"chunk_index": 4149,"x": 14279,"z": 421,"dimension": 1},{"entity_id": 144115188076052265,"chunk_index": 4150,"x": 14324,"z": 424,"dimension": 1},{"entity_id": 144115188076052269,"chunk_index": 4150,"x": 14332,"z": 424,"dimension": 1},{"entity_id": 144115188076052267,"chunk_index": 4150,"x": 14330,"z": 424,"dimension": 1},{"entity_id": 144115188076052371,"chunk_index": 4148,"x": 14176,"z": 430,"dimension": 1},{"entity_id": 144115188076052343,"chunk_index": 4150,"x": 14327,"z": 427,"dimension": 1},{"entity_id": 144115188076052553,"chunk_index": 4149,"x": 14231,"z": 433,"dimension": 1},{"entity_id": 144115188076052567,"chunk_index": 4149,"x": 14291,"z": 433,"dimension": 1},{"entity_id": 144115188076052657,"chunk_index": 4149,"x": 14216,"z": 436,"dimension": 1},{"entity_id": 144115188076052581,"chunk_index": 4150,"x": 14327,"z": 433,"dimension": 1},{"entity_id": 144115188076052649,"chunk_index": 4148,"x": 14201,"z": 436,"dimension": 1},{"entity_id": 144115188076052661,"chunk_index": 4149,"x": 14231,"z": 436,"dimension": 1},{"entity_id": 144115188076052663,"chunk_index": 4149,"x": 14236,"z": 436,"dimension": 1},{"entity_id": 144115188076052777,"chunk_index": 4149,"x": 14286,"z": 439,"dimension": 1},{"entity_id": 144115188076052687,"chunk_index": 4150,"x": 14307,"z": 436,"dimension": 1},{"entity_id": 144115188076052753,"chunk_index": 4148,"x": 14199,"z": 439,"dimension": 1},{"entity_id": 144115188076052779,"chunk_index": 4149,"x": 14287,"z": 439,"dimension": 1},{"entity_id": 144115188076052911,"chunk_index": 4149,"x": 14216,"z": 442,"dimension": 1},{"entity_id": 144115188076052825,"chunk_index": 4148,"x": 14156,"z": 442,"dimension": 1},{"entity_id": 144115188076052980,"chunk_index": 4149,"x": 14302,"z": 442,"dimension": 1},{"entity_id": 144115188076052992,"chunk_index": 4150,"x": 14321,"z": 442,"dimension": 1},{"entity_id": 144115188076053014,"chunk_index": 4148,"x": 14151,"z": 445,"dimension": 1},{"entity_id": 144115188076053036,"chunk_index": 4149,"x": 14219,"z": 445,"dimension": 1},{"entity_id": 144115188076053100,"chunk_index": 4150,"x": 14333,"z": 445,"dimension": 1},{"entity_id": 144115188076053156,"chunk_index": 4148,"x": 14189,"z": 448,"dimension": 1},{"entity_id": 144115188076053134,"chunk_index": 4148,"x": 14114,"z": 448,"dimension": 1},{"entity_id": 144115188076053096,"chunk_index": 4150,"x": 14328,"z": 445,"dimension": 1},{"entity_id": 144115188076053162,"chunk_index": 4148,"x": 14200,"z": 448,"dimension": 1},{"entity_id": 144115188076053262,"chunk_index": 4148,"x": 14114,"z": 451,"dimension": 1},{"entity_id": 144115188076053264,"chunk_index": 4148,"x": 14115,"z": 451,"dimension": 1},{"entity_id": 144115188076053290,"chunk_index": 4148,"x": 14205,"z": 451,"dimension": 1},{"entity_id": 144115188076053320,"chunk_index": 4149,"x": 14224,"z": 451,"dimension": 1},{"entity_id": 144115188076053342,"chunk_index": 4149,"x": 14289,"z": 451,"dimension": 1},{"entity_id": 144115188076053376,"chunk_index": 4148,"x": 14139,"z": 454,"dimension": 1},{"entity_id": 144115188076053464,"chunk_index": 4150,"x": 14311,"z": 454,"dimension": 1},{"entity_id": 144115188076053470,"chunk_index": 4150,"x": 14338,"z": 454,"dimension": 1},{"entity_id": 144115188076053400,"chunk_index": 4148,"x": 14155,"z": 454,"dimension": 1},{"entity_id": 144115188076053601,"chunk_index": 4148,"x": 14126,"z": 460,"dimension": 1},{"entity_id": 144115188076053474,"chunk_index": 4150,"x": 14350,"z": 454,"dimension": 1},{"entity_id": 144115188076053636,"chunk_index": 4149,"x": 14211,"z": 460,"dimension": 1},{"entity_id": 144115188076053620,"chunk_index": 4148,"x": 14176,"z": 460,"dimension": 1},{"entity_id": 144115188076053660,"chunk_index": 4150,"x": 14321,"z": 460,"dimension": 1},{"entity_id": 144115188076053706,"chunk_index": 4149,"x": 14228,"z": 463,"dimension": 1},{"entity_id": 144115188076053991,"chunk_index": 4148,"x": 14142,"z": 472,"dimension": 1},{"entity_id": 144115188076053851,"chunk_index": 4150,"x": 14359,"z": 466,"dimension": 1},{"entity_id": 144115188076053757,"chunk_index": 4148,"x": 14122,"z": 466,"dimension": 1},{"entity_id": 144115188076053993,"chunk_index": 4148,"x": 14153,"z": 472,"dimension": 1},{"entity_id": 144115188076054011,"chunk_index": 4148,"x": 14194,"z": 472,"dimension": 1},{"entity_id": 144115188076054015,"chunk_index": 4148,"x": 14199,"z": 472,"dimension": 1},{"entity_id": 144115188076054236,"chunk_index": 4148,"x": 14200,"z": 478,"dimension": 1},{"entity_id": 144115188076054244,"chunk_index": 4149,"x": 14240,"z": 478,"dimension": 1},{"entity_id": 144115188076054280,"chunk_index": 4150,"x": 14320,"z": 478,"dimension": 1},{"entity_id": 144115188076055406,"chunk_index": 4151,"x": 14486,"z": 433,"dimension": 1},{"entity_id": 144115188076055870,"chunk_index": 4152,"x": 14542,"z": 448,"dimension": 1},{"entity_id": 144115188076054294,"chunk_index": 4150,"x": 14342,"z": 478,"dimension": 1},{"entity_id": 144115188076055532,"chunk_index": 4152,"x": 14541,"z": 436,"dimension": 1},{"entity_id": 144115188076055948,"chunk_index": 4152,"x": 14545,"z": 451,"dimension": 1},{"entity_id": 144115188076055976,"chunk_index": 4152,"x": 14534,"z": 454,"dimension": 1},{"entity_id": 144115188076055954,"chunk_index": 4152,"x": 14555,"z": 451,"dimension": 1},{"entity_id": 144115188076056269,"chunk_index": 4152,"x": 14546,"z": 466,"dimension": 1},{"entity_id": 144115188076056105,"chunk_index": 4151,"x": 14488,"z": 460,"dimension": 1},{"entity_id": 144115188076056265,"chunk_index": 4152,"x": 14540,"z": 466,"dimension": 1},{"entity_id": 144115188076056392,"chunk_index": 4151,"x": 14450,"z": 472,"dimension": 1},{"entity_id": 144115188076056313,"chunk_index": 4151,"x": 14442,"z": 469,"dimension": 1},{"entity_id": 144115188076056275,"chunk_index": 4152,"x": 14552,"z": 466,"dimension": 1},{"entity_id": 144115188076056447,"chunk_index": 4152,"x": 14552,"z": 472,"dimension": 1},{"entity_id": 144115188076056488,"chunk_index": 4152,"x": 14585,"z": 472,"dimension": 1},{"entity_id": 144115188076056560,"chunk_index": 4152,"x": 14562,"z": 475,"dimension": 1},{"entity_id": 144115188076056540,"chunk_index": 4152,"x": 14507,"z": 475,"dimension": 1},{"entity_id": 144115188076075929,"chunk_index": 4145,"x": 13908,"z": 431,"dimension": 1},{"entity_id": 144115188076076070,"chunk_index": 4145,"x": 13904,"z": 440,"dimension": 1},{"entity_id": 144115188076076423,"chunk_index": 4145,"x": 13859,"z": 464,"dimension": 1},{"entity_id": 144115188076076174,"chunk_index": 4145,"x": 13909,"z": 446,"dimension": 1},{"entity_id": 144115188076075722,"chunk_index": 4145,"x": 13899,"z": 422,"dimension": 1},{"entity_id": 144115188076056620,"chunk_index": 4152,"x": 14543,"z": 478,"dimension": 1},{"entity_id": 144115188076076395,"chunk_index": 4145,"x": 13870,"z": 461,"dimension": 1},{"entity_id": 144115188076076072,"chunk_index": 4145,"x": 13909,"z": 440,"dimension": 1},{"entity_id": 144115188076076431,"chunk_index": 4145,"x": 13901,"z": 464,"dimension": 1},{"entity_id": 144115188076076465,"chunk_index": 4145,"x": 13875,"z": 467,"dimension": 1},{"entity_id": 144115188076076587,"chunk_index": 4145,"x": 13889,"z": 473,"dimension": 1},{"entity_id": 144115188076076900,"chunk_index": 4146,"x": 13994,"z": 392,"dimension": 1},{"entity_id": 144115188076076886,"chunk_index": 4146,"x": 13980,"z": 392,"dimension": 1},{"entity_id": 144115188076076896,"chunk_index": 4146,"x": 13990,"z": 392,"dimension": 1},{"entity_id": 144115188076076944,"chunk_index": 4147,"x": 14087,"z": 392,"dimension": 1},{"entity_id": 144115188076076908,"chunk_index": 4146,"x": 14011,"z": 392,"dimension": 1},{"entity_id": 144115188076076942,"chunk_index": 4147,"x": 14080,"z": 392,"dimension": 1},{"entity_id": 144115188076076987,"chunk_index": 4146,"x": 13974,"z": 395,"dimension": 1},{"entity_id": 144115188076077018,"chunk_index": 4147,"x": 14051,"z": 395,"dimension": 1},{"entity_id": 144115188076077054,"chunk_index": 4148,"x": 14139,"z": 395,"dimension": 1},{"entity_id": 144115188076077237,"chunk_index": 4148,"x": 14117,"z": 401,"dimension": 1},{"entity_id": 144115188076077148,"chunk_index": 4148,"x": 14125,"z": 398,"dimension": 1},{"entity_id": 144115188076076736,"chunk_index": 4147,"x": 14098,"z": 386,"dimension": 1},{"entity_id": 144115188076076826,"chunk_index": 4147,"x": 14045,"z": 389,"dimension": 1},{"entity_id": 144115188076076844,"chunk_index": 4147,"x": 14090,"z": 389,"dimension": 1},{"entity_id": 144115188076076699,"chunk_index": 4146,"x": 14000,"z": 386,"dimension": 1},{"entity_id": 144115188076077431,"chunk_index": 4146,"x": 13974,"z": 407,"dimension": 1},{"entity_id": 144115188076077494,"chunk_index": 4148,"x": 14127,"z": 407,"dimension": 1},{"entity_id": 144115188076077492,"chunk_index": 4148,"x": 14124,"z": 407,"dimension": 1},{"entity_id": 144115188076077532,"chunk_index": 4146,"x": 13964,"z": 410,"dimension": 1},{"entity_id": 144115188076077639,"chunk_index": 4146,"x": 13989,"z": 413,"dimension": 1},{"entity_id": 144115188076077580,"chunk_index": 4147,"x": 14049,"z": 410,"dimension": 1},{"entity_id": 144115188076077689,"chunk_index": 4147,"x": 14081,"z": 413,"dimension": 1},{"entity_id": 144115188076077701,"chunk_index": 4148,"x": 14111,"z": 413,"dimension": 1},{"entity_id": 144115188076077677,"chunk_index": 4147,"x": 14043,"z": 413,"dimension": 1},{"entity_id": 144115188076077713,"chunk_index": 4148,"x": 14139,"z": 413,"dimension": 1},{"entity_id": 144115188076077723,"chunk_index": 4148,"x": 14197,"z": 413,"dimension": 1},{"entity_id": 144115188076077745,"chunk_index": 4146,"x": 13952,"z": 416,"dimension": 1},{"entity_id": 144115188076077725,"chunk_index": 4148,"x": 14199,"z": 413,"dimension": 1},{"entity_id": 144115188076077861,"chunk_index": 4148,"x": 14194,"z": 416,"dimension": 1},{"entity_id": 144115188076077923,"chunk_index": 4148,"x": 14148,"z": 419,"dimension": 1},{"entity_id": 144115188076077911,"chunk_index": 4147,"x": 14099,"z": 419,"dimension": 1},{"entity_id": 144115188076077905,"chunk_index": 4147,"x": 14087,"z": 419,"dimension": 1},{"entity_id": 144115188076077881,"chunk_index": 4146,"x": 13969,"z": 419,"dimension": 1},{"entity_id": 144115188076077935,"chunk_index": 4148,"x": 14172,"z": 419,"dimension": 1},{"entity_id": 144115188076078093,"chunk_index": 4148,"x": 14143,"z": 422,"dimension": 1},{"entity_id": 144115188076077971,"chunk_index": 4146,"x": 13940,"z": 422,"dimension": 1},{"entity_id": 144115188076078075,"chunk_index": 4147,"x": 14098,"z": 422,"dimension": 1},{"entity_id": 144115188076077939,"chunk_index": 4148,"x": 14190,"z": 419,"dimension": 1},{"entity_id": 144115188076078143,"chunk_index": 4146,"x": 13958,"z": 425,"dimension": 1},{"entity_id": 144115188076078209,"chunk_index": 4148,"x": 14202,"z": 425,"dimension": 1},{"entity_id": 144115188076078277,"chunk_index": 4148,"x": 14196,"z": 428,"dimension": 1},{"entity_id": 144115188076078171,"chunk_index": 4147,"x": 14057,"z": 425,"dimension": 1},{"entity_id": 144115188076078273,"chunk_index": 4148,"x": 14191,"z": 428,"dimension": 1},{"entity_id": 144115188076078293,"chunk_index": 4146,"x": 13956,"z": 431,"dimension": 1},{"entity_id": 144115188076078385,"chunk_index": 4146,"x": 13978,"z": 434,"dimension": 1},{"entity_id": 144115188076078371,"chunk_index": 4146,"x": 13953,"z": 434,"dimension": 1},{"entity_id": 144115188076078379,"chunk_index": 4146,"x": 13966,"z": 434,"dimension": 1},{"entity_id": 144115188076078335,"chunk_index": 4147,"x": 14097,"z": 431,"dimension": 1},{"entity_id": 144115188076078337,"chunk_index": 4147,"x": 14103,"z": 431,"dimension": 1},{"entity_id": 144115188076078421,"chunk_index": 4148,"x": 14116,"z": 434,"dimension": 1},{"entity_id": 144115188076078487,"chunk_index": 4146,"x": 13941,"z": 437,"dimension": 1},{"entity_id": 144115188076078472,"chunk_index": 4148,"x": 14185,"z": 434,"dimension": 1},{"entity_id": 144115188076078557,"chunk_index": 4147,"x": 14105,"z": 437,"dimension": 1},{"entity_id": 144115188076078575,"chunk_index": 4148,"x": 14177,"z": 437,"dimension": 1},{"entity_id": 144115188076078579,"chunk_index": 4148,"x": 14181,"z": 437,"dimension": 1},{"entity_id": 144115188076078569,"chunk_index": 4148,"x": 14150,"z": 437,"dimension": 1},{"entity_id": 144115188076078617,"chunk_index": 4146,"x": 13962,"z": 440,"dimension": 1},{"entity_id": 144115188076078607,"chunk_index": 4146,"x": 13946,"z": 440,"dimension": 1},{"entity_id": 144115188076078631,"chunk_index": 4146,"x": 13982,"z": 440,"dimension": 1},{"entity_id": 144115188076078643,"chunk_index": 4147,"x": 14020,"z": 440,"dimension": 1},{"entity_id": 144115188076078727,"chunk_index": 4146,"x": 13965,"z": 443,"dimension": 1},{"entity_id": 144115188076078647,"chunk_index": 4147,"x": 14041,"z": 440,"dimension": 1},{"entity_id": 144115188076078729,"chunk_index": 4146,"x": 13966,"z": 443,"dimension": 1},{"entity_id": 144115188076078739,"chunk_index": 4146,"x": 13973,"z": 443,"dimension": 1},{"entity_id": 144115188076078846,"chunk_index": 4146,"x": 13954,"z": 446,"dimension": 1},{"entity_id": 144115188076078852,"chunk_index": 4146,"x": 13966,"z": 446,"dimension": 1},{"entity_id": 144115188076078790,"chunk_index": 4148,"x": 14112,"z": 443,"dimension": 1},{"entity_id": 144115188076078862,"chunk_index": 4146,"x": 13977,"z": 446,"dimension": 1},{"entity_id": 144115188076078876,"chunk_index": 4147,"x": 14035,"z": 446,"dimension": 1},{"entity_id": 144115188076078892,"chunk_index": 4147,"x": 14090,"z": 446,"dimension": 1},{"entity_id": 144115188076078940,"chunk_index": 4148,"x": 14201,"z": 446,"dimension": 1},{"entity_id": 144115188076078936,"chunk_index": 4148,"x": 14195,"z": 446,"dimension": 1},{"entity_id": 144115188076078938,"chunk_index": 4148,"x": 14200,"z": 446,"dimension": 1},{"entity_id": 144115188076079076,"chunk_index": 4148,"x": 14184,"z": 449,"dimension": 1},{"entity_id": 144115188076078994,"chunk_index": 4146,"x": 13992,"z": 449,"dimension": 1},{"entity_id": 144115188076079181,"chunk_index": 4147,"x": 14084,"z": 452,"dimension": 1},{"entity_id": 144115188076079141,"chunk_index": 4146,"x": 13961,"z": 452,"dimension": 1},{"entity_id": 144115188076079143,"chunk_index": 4146,"x": 13964,"z": 452,"dimension": 1},{"entity_id": 144115188076079191,"chunk_index": 4148,"x": 14120,"z": 452,"dimension": 1},{"entity_id": 144115188076079193,"chunk_index": 4148,"x": 14126,"z": 452,"dimension": 1},{"entity_id": 144115188076079195,"chunk_index": 4148,"x": 14128,"z": 452,"dimension": 1},{"entity_id": 144115188076079205,"chunk_index": 4148,"x": 14149,"z": 452,"dimension": 1},{"entity_id": 144115188076079211,"chunk_index": 4148,"x": 14156,"z": 452,"dimension": 1},{"entity_id": 144115188076079243,"chunk_index": 4146,"x": 13936,"z": 455,"dimension": 1},{"entity_id": 144115188076079327,"chunk_index": 4148,"x": 14132,"z": 455,"dimension": 1},{"entity_id": 144115188076079259,"chunk_index": 4146,"x": 13970,"z": 455,"dimension": 1},{"entity_id": 144115188076079305,"chunk_index": 4147,"x": 14057,"z": 455,"dimension": 1},{"entity_id": 144115188076079329,"chunk_index": 4148,"x": 14139,"z": 455,"dimension": 1},{"entity_id": 144115188076079343,"chunk_index": 4148,"x": 14201,"z": 455,"dimension": 1},{"entity_id": 144115188076079435,"chunk_index": 4148,"x": 14180,"z": 458,"dimension": 1},{"entity_id": 144115188076079519,"chunk_index": 4148,"x": 14177,"z": 461,"dimension": 1},{"entity_id": 144115188076079594,"chunk_index": 4146,"x": 14014,"z": 464,"dimension": 1},{"entity_id": 144115188076079891,"chunk_index": 4148,"x": 14139,"z": 470,"dimension": 1},{"entity_id": 144115188076079893,"chunk_index": 4148,"x": 14144,"z": 470,"dimension": 1},{"entity_id": 144115188076079895,"chunk_index": 4148,"x": 14151,"z": 470,"dimension": 1},{"entity_id": 144115188076080026,"chunk_index": 4148,"x": 14133,"z": 473,"dimension": 1},{"entity_id": 144115188076080040,"chunk_index": 4148,"x": 14181,"z": 473,"dimension": 1},{"entity_id": 144115188076080152,"chunk_index": 5147,"x": 14082,"z": 479,"dimension": 1},{"entity_id": 144115188076080052,"chunk_index": 4148,"x": 14201,"z": 473,"dimension": 1},{"entity_id": 144115188076080234,"chunk_index": 4150,"x": 14324,"z": 386,"dimension": 1},{"entity_id": 144115188076080192,"chunk_index": 5148,"x": 14181,"z": 479,"dimension": 1},{"entity_id": 144115188076080423,"chunk_index": 4150,"x": 14330,"z": 395,"dimension": 1},{"entity_id": 144115188076080617,"chunk_index": 4150,"x": 14333,"z": 401,"dimension": 1},{"entity_id": 144115188076080749,"chunk_index": 4150,"x": 14351,"z": 407,"dimension": 1},{"entity_id": 144115188076080823,"chunk_index": 4150,"x": 14341,"z": 410,"dimension": 1},{"entity_id": 144115188076080871,"chunk_index": 4149,"x": 14274,"z": 413,"dimension": 1},{"entity_id": 144115188076080651,"chunk_index": 4150,"x": 14332,"z": 404,"dimension": 1},{"entity_id": 144115188076080879,"chunk_index": 4150,"x": 14303,"z": 413,"dimension": 1},{"entity_id": 144115188076081097,"chunk_index": 4149,"x": 14210,"z": 419,"dimension": 1},{"entity_id": 144115188076081123,"chunk_index": 4149,"x": 14296,"z": 419,"dimension": 1},{"entity_id": 144115188076081207,"chunk_index": 4150,"x": 14314,"z": 422,"dimension": 1},{"entity_id": 144115188076081209,"chunk_index": 4150,"x": 14320,"z": 422,"dimension": 1},{"entity_id": 144115188076081313,"chunk_index": 4150,"x": 14326,"z": 425,"dimension": 1},{"entity_id": 144115188076081311,"chunk_index": 4150,"x": 14324,"z": 425,"dimension": 1},{"entity_id": 144115188076081563,"chunk_index": 4150,"x": 14306,"z": 431,"dimension": 1},{"entity_id": 144115188076081484,"chunk_index": 4150,"x": 14358,"z": 428,"dimension": 1},{"entity_id": 144115188076081458,"chunk_index": 4150,"x": 14308,"z": 428,"dimension": 1},{"entity_id": 144115188076081652,"chunk_index": 4149,"x": 14227,"z": 434,"dimension": 1},{"entity_id": 144115188076081658,"chunk_index": 4149,"x": 14295,"z": 434,"dimension": 1},{"entity_id": 144115188076081668,"chunk_index": 4150,"x": 14318,"z": 434,"dimension": 1},{"entity_id": 144115188076081684,"chunk_index": 4150,"x": 14347,"z": 434,"dimension": 1},{"entity_id": 144115188076081662,"chunk_index": 4150,"x": 14307,"z": 434,"dimension": 1},{"entity_id": 144115188076081708,"chunk_index": 4151,"x": 14483,"z": 434,"dimension": 1},{"entity_id": 144115188076081706,"chunk_index": 4151,"x": 14480,"z": 434,"dimension": 1},{"entity_id": 144115188076081774,"chunk_index": 4151,"x": 14477,"z": 437,"dimension": 1},{"entity_id": 144115188076081714,"chunk_index": 4149,"x": 14212,"z": 437,"dimension": 1},{"entity_id": 144115188076081744,"chunk_index": 4150,"x": 14327,"z": 437,"dimension": 1},{"entity_id": 144115188076081923,"chunk_index": 4149,"x": 14213,"z": 443,"dimension": 1},{"entity_id": 144115188076081942,"chunk_index": 4149,"x": 14286,"z": 443,"dimension": 1},{"entity_id": 144115188076082018,"chunk_index": 4149,"x": 14254,"z": 446,"dimension": 1},{"entity_id": 144115188076081960,"chunk_index": 4150,"x": 14315,"z": 443,"dimension": 1},{"entity_id": 144115188076081958,"chunk_index": 4150,"x": 14314,"z": 443,"dimension": 1},{"entity_id": 144115188076082044,"chunk_index": 4150,"x": 14345,"z": 446,"dimension": 1},{"entity_id": 144115188076082078,"chunk_index": 4149,"x": 14213,"z": 449,"dimension": 1},{"entity_id": 144115188076082172,"chunk_index": 4149,"x": 14219,"z": 452,"dimension": 1},{"entity_id": 144115188076082218,"chunk_index": 4150,"x": 14328,"z": 452,"dimension": 1},{"entity_id": 144115188076082437,"chunk_index": 4151,"x": 14489,"z": 458,"dimension": 1},{"entity_id": 144115188076082290,"chunk_index": 4150,"x": 14318,"z": 455,"dimension": 1},{"entity_id": 144115188076082447,"chunk_index": 4149,"x": 14225,"z": 461,"dimension": 1},{"entity_id": 144115188076082481,"chunk_index": 4150,"x": 14321,"z": 461,"dimension": 1},{"entity_id": 144115188076082533,"chunk_index": 4149,"x": 14227,"z": 464,"dimension": 1},{"entity_id": 144115188076082535,"chunk_index": 4149,"x": 14237,"z": 464,"dimension": 1},{"entity_id": 144115188076082753,"chunk_index": 4151,"x": 14469,"z": 467,"dimension": 1},{"entity_id": 144115188076082759,"chunk_index": 4151,"x": 14474,"z": 467,"dimension": 1},{"entity_id": 144115188076082813,"chunk_index": 4150,"x": 14333,"z": 470,"dimension": 1},{"entity_id": 144115188076083114,"chunk_index": 5149,"x": 14298,"z": 479,"dimension": 1},{"entity_id": 144115188076082895,"chunk_index": 4150,"x": 14322,"z": 473,"dimension": 1},{"entity_id": 144115188076084020,"chunk_index": 4152,"x": 14521,"z": 428,"dimension": 1},{"entity_id": 144115188076084119,"chunk_index": 4152,"x": 14540,"z": 431,"dimension": 1},{"entity_id": 144115188076084121,"chunk_index": 4152,"x": 14541,"z": 431,"dimension": 1},{"entity_id": 144115188076084211,"chunk_index": 4152,"x": 14517,"z": 437,"dimension": 1},{"entity_id": 144115188076084433,"chunk_index": 4152,"x": 14513,"z": 455,"dimension": 1},{"entity_id": 144115188076084798,"chunk_index": 4152,"x": 14551,"z": 470,"dimension": 1},{"entity_id": 144115188076084639,"chunk_index": 4152,"x": 14516,"z": 464,"dimension": 1},{"entity_id": 144115188076084873,"chunk_index": 4152,"x": 14540,"z": 473,"dimension": 1},{"entity_id": 144115188076084943,"chunk_index": 4152,"x": 14545,"z": 476,"dimension": 1},{"entity_id": 144115188076106242,"chunk_index": 5145,"x": 13916,"z": 480,"dimension": 1},{"entity_id": 144115188076106326,"chunk_index": 5145,"x": 13892,"z": 483,"dimension": 1},{"entity_id": 144115188076106341,"chunk_index": 5146,"x": 13928,"z": 483,"dimension": 1},{"entity_id": 144115188076106582,"chunk_index": 5146,"x": 13982,"z": 492,"dimension": 1},{"entity_id": 144115188076106722,"chunk_index": 5145,"x": 13906,"z": 498,"dimension": 1},{"entity_id": 144115188076106570,"chunk_index": 5146,"x": 13940,"z": 492,"dimension": 1},{"entity_id": 144115188076106726,"chunk_index": 5145,"x": 13909,"z": 498,"dimension": 1},{"entity_id": 144115188076106838,"chunk_index": 5146,"x": 13964,"z": 501,"dimension": 1},{"entity_id": 144115188076106804,"chunk_index": 5145,"x": 13857,"z": 501,"dimension": 1},{"entity_id": 144115188076106888,"chunk_index": 5145,"x": 13854,"z": 504,"dimension": 1},{"entity_id": 144115188076106935,"chunk_index": 5145,"x": 13872,"z": 504,"dimension": 1},{"entity_id": 144115188076107005,"chunk_index": 5145,"x": 13845,"z": 507,"dimension": 1},{"entity_id": 144115188076107055,"chunk_index": 5146,"x": 13928,"z": 507,"dimension": 1},{"entity_id": 144115188076107213,"chunk_index": 5146,"x": 13999,"z": 510,"dimension": 1},{"entity_id": 144115188076107340,"chunk_index": 5145,"x": 13857,"z": 516,"dimension": 1},{"entity_id": 144115188076107404,"chunk_index": 5146,"x": 14000,"z": 516,"dimension": 1},{"entity_id": 144115188076107645,"chunk_index": 5146,"x": 13922,"z": 525,"dimension": 1},{"entity_id": 144115188076107649,"chunk_index": 5146,"x": 13932,"z": 525,"dimension": 1},{"entity_id": 144115188076107753,"chunk_index": 5146,"x": 13974,"z": 528,"dimension": 1},{"entity_id": 144115188076107757,"chunk_index": 5146,"x": 13989,"z": 528,"dimension": 1},{"entity_id": 144115188076107969,"chunk_index": 5146,"x": 13923,"z": 534,"dimension": 1},{"entity_id": 144115188076108118,"chunk_index": 5146,"x": 14004,"z": 537,"dimension": 1},{"entity_id": 144115188076108182,"chunk_index": 5145,"x": 13908,"z": 540,"dimension": 1},{"entity_id": 144115188076108343,"chunk_index": 5146,"x": 14015,"z": 543,"dimension": 1},{"entity_id": 144115188076108337,"chunk_index": 5146,"x": 14001,"z": 543,"dimension": 1},{"entity_id": 144115188076108442,"chunk_index": 5146,"x": 13972,"z": 546,"dimension": 1},{"entity_id": 144115188076108575,"chunk_index": 5146,"x": 14007,"z": 549,"dimension": 1},{"entity_id": 144115188076108653,"chunk_index": 5146,"x": 13976,"z": 552,"dimension": 1},{"entity_id": 144115188076108800,"chunk_index": 5145,"x": 13845,"z": 558,"dimension": 1},{"entity_id": 144115188076108873,"chunk_index": 5146,"x": 13978,"z": 558,"dimension": 1},{"entity_id": 144115188076108913,"chunk_index": 5145,"x": 13860,"z": 561,"dimension": 1},{"entity_id": 144115188076108881,"chunk_index": 5146,"x": 13992,"z": 558,"dimension": 1},{"entity_id": 144115188076108965,"chunk_index": 5146,"x": 14013,"z": 561,"dimension": 1},{"entity_id": 144115188076109023,"chunk_index": 5146,"x": 13934,"z": 564,"dimension": 1},{"entity_id": 144115188076109081,"chunk_index": 5145,"x": 13836,"z": 567,"dimension": 1},{"entity_id": 144115188076109031,"chunk_index": 5146,"x": 13954,"z": 564,"dimension": 1},{"entity_id": 144115188076109101,"chunk_index": 5145,"x": 13865,"z": 567,"dimension": 1},{"entity_id": 144115188076109218,"chunk_index": 5146,"x": 14015,"z": 567,"dimension": 1},{"entity_id": 144115188076109232,"chunk_index": 5145,"x": 13826,"z": 570,"dimension": 1},{"entity_id": 144115188076109242,"chunk_index": 5145,"x": 13844,"z": 570,"dimension": 1},{"entity_id": 144115188076109246,"chunk_index": 5145,"x": 13850,"z": 570,"dimension": 1},{"entity_id": 144115188076109475,"chunk_index": 5147,"x": 14077,"z": 480,"dimension": 1},{"entity_id": 144115188076109274,"chunk_index": 5145,"x": 13886,"z": 570,"dimension": 1},{"entity_id": 144115188076109490,"chunk_index": 5148,"x": 14118,"z": 480,"dimension": 1},{"entity_id": 144115188076109622,"chunk_index": 5149,"x": 14241,"z": 480,"dimension": 1},{"entity_id": 144115188076109732,"chunk_index": 5148,"x": 14174,"z": 483,"dimension": 1},{"entity_id": 144115188076109875,"chunk_index": 5148,"x": 14132,"z": 486,"dimension": 1},{"entity_id": 144115188076109750,"chunk_index": 5149,"x": 14209,"z": 483,"dimension": 1},{"entity_id": 144115188076109881,"chunk_index": 5148,"x": 14144,"z": 486,"dimension": 1},{"entity_id": 144115188076109887,"chunk_index": 5148,"x": 14148,"z": 486,"dimension": 1},{"entity_id": 144115188076109891,"chunk_index": 5148,"x": 14151,"z": 486,"dimension": 1},{"entity_id": 144115188076109921,"chunk_index": 5149,"x": 14216,"z": 486,"dimension": 1},{"entity_id": 144115188076109913,"chunk_index": 5148,"x": 14200,"z": 486,"dimension": 1},{"entity_id": 144115188076110003,"chunk_index": 5149,"x": 14217,"z": 489,"dimension": 1},{"entity_id": 144115188076109925,"chunk_index": 5149,"x": 14233,"z": 486,"dimension": 1},{"entity_id": 144115188076110062,"chunk_index": 5147,"x": 14016,"z": 492,"dimension": 1},{"entity_id": 144115188076109991,"chunk_index": 5148,"x": 14201,"z": 489,"dimension": 1},{"entity_id": 144115188076110170,"chunk_index": 5149,"x": 14208,"z": 495,"dimension": 1},{"entity_id": 144115188076110276,"chunk_index": 5148,"x": 14195,"z": 498,"dimension": 1},{"entity_id": 144115188076110316,"chunk_index": 5149,"x": 14249,"z": 498,"dimension": 1},{"entity_id": 144115188076110334,"chunk_index": 5147,"x": 14045,"z": 501,"dimension": 1},{"entity_id": 144115188076110340,"chunk_index": 5147,"x": 14056,"z": 501,"dimension": 1},{"entity_id": 144115188076110417,"chunk_index": 5149,"x": 14221,"z": 501,"dimension": 1},{"entity_id": 144115188076110615,"chunk_index": 5148,"x": 14196,"z": 507,"dimension": 1},{"entity_id": 144115188076110542,"chunk_index": 5149,"x": 14222,"z": 504,"dimension": 1},{"entity_id": 144115188076110540,"chunk_index": 5149,"x": 14219,"z": 504,"dimension": 1},{"entity_id": 144115188076110514,"chunk_index": 5148,"x": 14181,"z": 504,"dimension": 1},{"entity_id": 144115188076110795,"chunk_index": 5148,"x": 14177,"z": 510,"dimension": 1},{"entity_id": 144115188076110630,"chunk_index": 5149,"x": 14222,"z": 507,"dimension": 1},{"entity_id": 144115188076110799,"chunk_index": 5148,"x": 14187,"z": 510,"dimension": 1},{"entity_id": 144115188076110797,"chunk_index": 5148,"x": 14185,"z": 510,"dimension": 1},{"entity_id": 144115188076110811,"chunk_index": 5149,"x": 14214,"z": 510,"dimension": 1},{"entity_id": 144115188076110861,"chunk_index": 5147,"x": 14036,"z": 513,"dimension": 1},{"entity_id": 144115188076110925,"chunk_index": 5148,"x": 14202,"z": 513,"dimension": 1},{"entity_id": 144115188076110905,"chunk_index": 5148,"x": 14133,"z": 513,"dimension": 1},{"entity_id": 144115188076110819,"chunk_index": 5149,"x": 14224,"z": 510,"dimension": 1},{"entity_id": 144115188076110875,"chunk_index": 5147,"x": 14068,"z": 513,"dimension": 1},{"entity_id": 144115188076111032,"chunk_index": 5149,"x": 14218,"z": 516,"dimension": 1},{"entity_id": 144115188076111001,"chunk_index": 5148,"x": 14174,"z": 516,"dimension": 1},{"entity_id": 144115188076111244,"chunk_index": 5147,"x": 14065,"z": 522,"dimension": 1},{"entity_id": 144115188076111346,"chunk_index": 5147,"x": 14036,"z": 525,"dimension": 1},{"entity_id": 144115188076111300,"chunk_index": 5149,"x": 14217,"z": 522,"dimension": 1},{"entity_id": 144115188076111372,"chunk_index": 5147,"x": 14097,"z": 525,"dimension": 1},{"entity_id": 144115188076111448,"chunk_index": 5149,"x": 14251,"z": 525,"dimension": 1},{"entity_id": 144115188076111486,"chunk_index": 5147,"x": 14065,"z": 528,"dimension": 1},{"entity_id": 144115188076111302,"chunk_index": 5149,"x": 14218,"z": 522,"dimension": 1},{"entity_id": 144115188076111480,"chunk_index": 5147,"x": 14047,"z": 528,"dimension": 1},{"entity_id": 144115188076111548,"chunk_index": 5149,"x": 14211,"z": 528,"dimension": 1},{"entity_id": 144115188076111564,"chunk_index": 5149,"x": 14248,"z": 528,"dimension": 1},{"entity_id": 144115188076111599,"chunk_index": 5147,"x": 14082,"z": 531,"dimension": 1},{"entity_id": 144115188076111659,"chunk_index": 5148,"x": 14203,"z": 531,"dimension": 1},{"entity_id": 144115188076111727,"chunk_index": 5147,"x": 14036,"z": 534,"dimension": 1},{"entity_id": 144115188076111906,"chunk_index": 5149,"x": 14261,"z": 534,"dimension": 1},{"entity_id": 144115188076111986,"chunk_index": 5148,"x": 14191,"z": 537,"dimension": 1},{"entity_id": 144115188076112066,"chunk_index": 5147,"x": 14069,"z": 540,"dimension": 1},{"entity_id": 144115188076112000,"chunk_index": 5149,"x": 14237,"z": 537,"dimension": 1},{"entity_id": 144115188076112149,"chunk_index": 5149,"x": 14244,"z": 540,"dimension": 1},{"entity_id": 144115188076112030,"chunk_index": 5147,"x": 14017,"z": 540,"dimension": 1},{"entity_id": 144115188076112278,"chunk_index": 5149,"x": 14237,"z": 543,"dimension": 1},{"entity_id": 144115188076112183,"chunk_index": 5149,"x": 14294,"z": 540,"dimension": 1},{"entity_id": 144115188076112382,"chunk_index": 5148,"x": 14196,"z": 546,"dimension": 1},{"entity_id": 144115188076112380,"chunk_index": 5148,"x": 14176,"z": 546,"dimension": 1},{"entity_id": 144115188076112770,"chunk_index": 5147,"x": 14054,"z": 555,"dimension": 1},{"entity_id": 144115188076112471,"chunk_index": 5147,"x": 14078,"z": 549,"dimension": 1},{"entity_id": 144115188076112392,"chunk_index": 5149,"x": 14229,"z": 546,"dimension": 1},{"entity_id": 144115188076112746,"chunk_index": 5149,"x": 14298,"z": 552,"dimension": 1},{"entity_id": 144115188076112405,"chunk_index": 5149,"x": 14236,"z": 546,"dimension": 1},{"entity_id": 144115188076112449,"chunk_index": 5147,"x": 14042,"z": 549,"dimension": 1},{"entity_id": 144115188076112784,"chunk_index": 5147,"x": 14076,"z": 555,"dimension": 1},{"entity_id": 144115188076112788,"chunk_index": 5147,"x": 14090,"z": 555,"dimension": 1},{"entity_id": 144115188076112826,"chunk_index": 5148,"x": 14191,"z": 555,"dimension": 1},{"entity_id": 144115188076112918,"chunk_index": 5149,"x": 14299,"z": 555,"dimension": 1},{"entity_id": 144115188076112940,"chunk_index": 5147,"x": 14053,"z": 558,"dimension": 1},{"entity_id": 144115188076112880,"chunk_index": 5149,"x": 14224,"z": 555,"dimension": 1},{"entity_id": 144115188076113034,"chunk_index": 5149,"x": 14237,"z": 558,"dimension": 1},{"entity_id": 144115188076113572,"chunk_index": 5148,"x": 14199,"z": 567,"dimension": 1},{"entity_id": 144115188076112962,"chunk_index": 5147,"x": 14075,"z": 558,"dimension": 1},{"entity_id": 144115188076112966,"chunk_index": 5147,"x": 14086,"z": 558,"dimension": 1},{"entity_id": 144115188076113684,"chunk_index": 5148,"x": 14179,"z": 570,"dimension": 1},{"entity_id": 144115188076113751,"chunk_index": 5147,"x": 14052,"z": 573,"dimension": 1},{"entity_id": 144115188076113753,"chunk_index": 5147,"x": 14054,"z": 573,"dimension": 1},{"entity_id": 144115188076113763,"chunk_index": 5147,"x": 14069,"z": 573,"dimension": 1},{"entity_id": 144115188076113852,"chunk_index": 5148,"x": 14195,"z": 573,"dimension": 1},{"entity_id": 144115188076113765,"chunk_index": 5147,"x": 14070,"z": 573,"dimension": 1},{"entity_id": 144115188076113886,"chunk_index": 5149,"x": 14260,"z": 573,"dimension": 1},{"entity_id": 144115188076113904,"chunk_index": 5149,"x": 14301,"z": 573,"dimension": 1},{"entity_id": 144115188076113934,"chunk_index": 5150,"x": 14334,"z": 480,"dimension": 1},{"entity_id": 144115188076113958,"chunk_index": 5151,"x": 14489,"z": 480,"dimension": 1},{"entity_id": 144115188076113986,"chunk_index": 5152,"x": 14558,"z": 480,"dimension": 1},{"entity_id": 144115188076114026,"chunk_index": 5150,"x": 14366,"z": 483,"dimension": 1},{"entity_id": 144115188076114052,"chunk_index": 5152,"x": 14521,"z": 483,"dimension": 1},{"entity_id": 144115188076114203,"chunk_index": 5152,"x": 14541,"z": 486,"dimension": 1},{"entity_id": 144115188076114127,"chunk_index": 5152,"x": 14589,"z": 483,"dimension": 1},{"entity_id": 144115188076114233,"chunk_index": 5152,"x": 14585,"z": 486,"dimension": 1},{"entity_id": 144115188076114285,"chunk_index": 5152,"x": 14534,"z": 489,"dimension": 1},{"entity_id": 144115188076114327,"chunk_index": 5152,"x": 14581,"z": 489,"dimension": 1},{"entity_id": 144115188076114261,"chunk_index": 5150,"x": 14361,"z": 489,"dimension": 1},{"entity_id": 144115188076114303,"chunk_index": 5152,"x": 14561,"z": 489,"dimension": 1},{"entity_id": 144115188076114377,"chunk_index": 5152,"x": 14514,"z": 492,"dimension": 1},{"entity_id": 144115188076114341,"chunk_index": 5150,"x": 14369,"z": 492,"dimension": 1},{"entity_id": 144115188076114485,"chunk_index": 5151,"x": 14456,"z": 495,"dimension": 1},{"entity_id": 144115188076114435,"chunk_index": 5152,"x": 14586,"z": 492,"dimension": 1},{"entity_id": 144115188076114421,"chunk_index": 5152,"x": 14546,"z": 492,"dimension": 1},{"entity_id": 144115188076114496,"chunk_index": 5152,"x": 14497,"z": 495,"dimension": 1},{"entity_id": 144115188076114617,"chunk_index": 5150,"x": 14388,"z": 498,"dimension": 1},{"entity_id": 144115188076114579,"chunk_index": 5152,"x": 14567,"z": 495,"dimension": 1},{"entity_id": 144115188076114619,"chunk_index": 5150,"x": 14390,"z": 498,"dimension": 1},{"entity_id": 144115188076114506,"chunk_index": 5152,"x": 14510,"z": 495,"dimension": 1},{"entity_id": 144115188076114664,"chunk_index": 5151,"x": 14487,"z": 498,"dimension": 1},{"entity_id": 144115188076114666,"chunk_index": 5151,"x": 14488,"z": 498,"dimension": 1},{"entity_id": 144115188076114706,"chunk_index": 5152,"x": 14587,"z": 498,"dimension": 1},{"entity_id": 144115188076114690,"chunk_index": 5152,"x": 14531,"z": 498,"dimension": 1},{"entity_id": 144115188076114747,"chunk_index": 5150,"x": 14346,"z": 501,"dimension": 1},{"entity_id": 144115188076114851,"chunk_index": 5151,"x": 14488,"z": 501,"dimension": 1},{"entity_id": 144115188076114853,"chunk_index": 5151,"x": 14495,"z": 501,"dimension": 1},{"entity_id": 144115188076114883,"chunk_index": 5152,"x": 14540,"z": 501,"dimension": 1},{"entity_id": 144115188076114890,"chunk_index": 5152,"x": 14543,"z": 501,"dimension": 1},{"entity_id": 144115188076114924,"chunk_index": 5150,"x": 14327,"z": 504,"dimension": 1},{"entity_id": 144115188076115443,"chunk_index": 5152,"x": 14544,"z": 510,"dimension": 1},{"entity_id": 144115188076114987,"chunk_index": 5151,"x": 14400,"z": 504,"dimension": 1},{"entity_id": 144115188076115258,"chunk_index": 5152,"x": 14501,"z": 507,"dimension": 1},{"entity_id": 144115188076115501,"chunk_index": 5150,"x": 14369,"z": 513,"dimension": 1},{"entity_id": 144115188076115627,"chunk_index": 5150,"x": 14346,"z": 516,"dimension": 1},{"entity_id": 144115188076115637,"chunk_index": 5150,"x": 14361,"z": 516,"dimension": 1},{"entity_id": 144115188076115639,"chunk_index": 5150,"x": 14363,"z": 516,"dimension": 1},{"entity_id": 144115188076115643,"chunk_index": 5150,"x": 14382,"z": 516,"dimension": 1},{"entity_id": 144115188076115676,"chunk_index": 5151,"x": 14470,"z": 516,"dimension": 1},{"entity_id": 144115188076115649,"chunk_index": 5150,"x": 14391,"z": 516,"dimension": 1},{"entity_id": 144115188076115684,"chunk_index": 5152,"x": 14499,"z": 516,"dimension": 1},{"entity_id": 144115188076115770,"chunk_index": 5150,"x": 14382,"z": 519,"dimension": 1},{"entity_id": 144115188076115856,"chunk_index": 5150,"x": 14328,"z": 522,"dimension": 1},{"entity_id": 144115188076116038,"chunk_index": 5150,"x": 14347,"z": 525,"dimension": 1},{"entity_id": 144115188076115921,"chunk_index": 5150,"x": 14376,"z": 522,"dimension": 1},{"entity_id": 144115188076116078,"chunk_index": 5151,"x": 14430,"z": 525,"dimension": 1},{"entity_id": 144115188076116098,"chunk_index": 5152,"x": 14538,"z": 525,"dimension": 1},{"entity_id": 144115188076116186,"chunk_index": 5151,"x": 14456,"z": 528,"dimension": 1},{"entity_id": 144115188076116188,"chunk_index": 5151,"x": 14463,"z": 528,"dimension": 1},{"entity_id": 144115188076116329,"chunk_index": 5150,"x": 14345,"z": 534,"dimension": 1},{"entity_id": 144115188076116387,"chunk_index": 5152,"x": 14509,"z": 534,"dimension": 1},{"entity_id": 144115188076116451,"chunk_index": 5150,"x": 14369,"z": 537,"dimension": 1},{"entity_id": 144115188076116385,"chunk_index": 5152,"x": 14501,"z": 534,"dimension": 1},{"entity_id": 144115188076116514,"chunk_index": 5152,"x": 14498,"z": 537,"dimension": 1},{"entity_id": 144115188076116389,"chunk_index": 5152,"x": 14514,"z": 534,"dimension": 1},{"entity_id": 144115188076116701,"chunk_index": 5150,"x": 14360,"z": 543,"dimension": 1},{"entity_id": 144115188076116757,"chunk_index": 5151,"x": 14490,"z": 543,"dimension": 1},{"entity_id": 144115188076116759,"chunk_index": 5151,"x": 14495,"z": 543,"dimension": 1},{"entity_id": 144115188076116798,"chunk_index": 5150,"x": 14361,"z": 546,"dimension": 1},{"entity_id": 144115188076117000,"chunk_index": 5150,"x": 14349,"z": 549,"dimension": 1},{"entity_id": 144115188076116990,"chunk_index": 5150,"x": 14304,"z": 549,"dimension": 1},{"entity_id": 144115188076117002,"chunk_index": 5150,"x": 14355,"z": 549,"dimension": 1},{"entity_id": 144115188076117010,"chunk_index": 5150,"x": 14383,"z": 549,"dimension": 1},{"entity_id": 144115188076117064,"chunk_index": 5152,"x": 14543,"z": 549,"dimension": 1},{"entity_id": 144115188076116996,"chunk_index": 5150,"x": 14347,"z": 549,"dimension": 1},{"entity_id": 144115188076117118,"chunk_index": 5150,"x": 14382,"z": 552,"dimension": 1},{"entity_id": 144115188076117126,"chunk_index": 5150,"x": 14396,"z": 552,"dimension": 1},{"entity_id": 144115188076117160,"chunk_index": 5152,"x": 14518,"z": 552,"dimension": 1},{"entity_id": 144115188076117218,"chunk_index": 5150,"x": 14390,"z": 555,"dimension": 1},{"entity_id": 144115188076117220,"chunk_index": 5151,"x": 14403,"z": 555,"dimension": 1},{"entity_id": 144115188076117270,"chunk_index": 5151,"x": 14495,"z": 555,"dimension": 1},{"entity_id": 144115188076117282,"chunk_index": 5152,"x": 14532,"z": 555,"dimension": 1},{"entity_id": 144115188076117321,"chunk_index": 5152,"x": 14556,"z": 555,"dimension": 1},{"entity_id": 144115188076117280,"chunk_index": 5152,"x": 14525,"z": 555,"dimension": 1},{"entity_id": 144115188076117361,"chunk_index": 5150,"x": 14373,"z": 558,"dimension": 1},{"entity_id": 144115188076117349,"chunk_index": 5150,"x": 14332,"z": 558,"dimension": 1},{"entity_id": 144115188076117523,"chunk_index": 5152,"x": 14526,"z": 561,"dimension": 1},{"entity_id": 144115188076117511,"chunk_index": 5151,"x": 14494,"z": 561,"dimension": 1},{"entity_id": 144115188076117525,"chunk_index": 5152,"x": 14527,"z": 561,"dimension": 1},{"entity_id": 144115188076117723,"chunk_index": 5150,"x": 14356,"z": 567,"dimension": 1},{"entity_id": 144115188076117765,"chunk_index": 5152,"x": 14504,"z": 567,"dimension": 1},{"entity_id": 144115188076117733,"chunk_index": 5150,"x": 14380,"z": 567,"dimension": 1},{"entity_id": 144115188076117901,"chunk_index": 5152,"x": 14519,"z": 570,"dimension": 1},{"entity_id": 144115188076117860,"chunk_index": 5150,"x": 14380,"z": 570,"dimension": 1},{"entity_id": 144115188076117997,"chunk_index": 5150,"x": 14397,"z": 573,"dimension": 1},{"entity_id": 144115188076118401,"chunk_index": 5153,"x": 14602,"z": 498,"dimension": 1},{"entity_id": 144115188076118155,"chunk_index": 5153,"x": 14602,"z": 486,"dimension": 1},{"entity_id": 144115188076118537,"chunk_index": 5153,"x": 14609,"z": 507,"dimension": 1},{"entity_id": 144115188076118527,"chunk_index": 5153,"x": 14592,"z": 507,"dimension": 1},{"entity_id": 144115188076118591,"chunk_index": 5153,"x": 14606,"z": 510,"dimension": 1},{"entity_id": 144115188076140365,"chunk_index": 5145,"x": 13916,"z": 481,"dimension": 1},{"entity_id": 144115188076118765,"chunk_index": 5153,"x": 14613,"z": 519,"dimension": 1},{"entity_id": 144115188076140426,"chunk_index": 5147,"x": 14073,"z": 481,"dimension": 1},{"entity_id": 144115188076140464,"chunk_index": 5146,"x": 13970,"z": 484,"dimension": 1},{"entity_id": 144115188076140546,"chunk_index": 5146,"x": 13988,"z": 487,"dimension": 1},{"entity_id": 144115188076140600,"chunk_index": 5147,"x": 14103,"z": 487,"dimension": 1},{"entity_id": 144115188076140722,"chunk_index": 5146,"x": 13998,"z": 493,"dimension": 1},{"entity_id": 144115188076140851,"chunk_index": 5146,"x": 13974,"z": 499,"dimension": 1},{"entity_id": 144115188076140738,"chunk_index": 5147,"x": 14053,"z": 493,"dimension": 1},{"entity_id": 144115188076140907,"chunk_index": 5145,"x": 13906,"z": 502,"dimension": 1},{"entity_id": 144115188076140968,"chunk_index": 5145,"x": 13902,"z": 505,"dimension": 1},{"entity_id": 144115188076141087,"chunk_index": 5145,"x": 13907,"z": 508,"dimension": 1},{"entity_id": 144115188076140926,"chunk_index": 5146,"x": 13993,"z": 502,"dimension": 1},{"entity_id": 144115188076141085,"chunk_index": 5145,"x": 13903,"z": 508,"dimension": 1},{"entity_id": 144115188076141113,"chunk_index": 5146,"x": 13986,"z": 508,"dimension": 1},{"entity_id": 144115188076141141,"chunk_index": 5147,"x": 14084,"z": 508,"dimension": 1},{"entity_id": 144115188076141095,"chunk_index": 5146,"x": 13934,"z": 508,"dimension": 1},{"entity_id": 144115188076141247,"chunk_index": 5146,"x": 14014,"z": 511,"dimension": 1},{"entity_id": 144115188076141265,"chunk_index": 5147,"x": 14075,"z": 511,"dimension": 1},{"entity_id": 144115188076141313,"chunk_index": 5146,"x": 14002,"z": 514,"dimension": 1},{"entity_id": 144115188076141271,"chunk_index": 5145,"x": 13871,"z": 514,"dimension": 1},{"entity_id": 144115188076141490,"chunk_index": 5147,"x": 14093,"z": 517,"dimension": 1},{"entity_id": 144115188076141572,"chunk_index": 5145,"x": 13849,"z": 523,"dimension": 1},{"entity_id": 144115188076141620,"chunk_index": 5146,"x": 14010,"z": 523,"dimension": 1},{"entity_id": 144115188076141622,"chunk_index": 5146,"x": 14012,"z": 523,"dimension": 1},{"entity_id": 144115188076141636,"chunk_index": 5147,"x": 14082,"z": 523,"dimension": 1},{"entity_id": 144115188076141740,"chunk_index": 5147,"x": 14068,"z": 526,"dimension": 1},{"entity_id": 144115188076141903,"chunk_index": 5145,"x": 13913,"z": 532,"dimension": 1},{"entity_id": 144115188076141848,"chunk_index": 5145,"x": 13850,"z": 532,"dimension": 1},{"entity_id": 144115188076142093,"chunk_index": 5147,"x": 14042,"z": 538,"dimension": 1},{"entity_id": 144115188076142125,"chunk_index": 5147,"x": 14080,"z": 538,"dimension": 1},{"entity_id": 144115188076142206,"chunk_index": 5146,"x": 13969,"z": 541,"dimension": 1},{"entity_id": 144115188076142220,"chunk_index": 5146,"x": 14013,"z": 541,"dimension": 1},{"entity_id": 144115188076142222,"chunk_index": 5147,"x": 14016,"z": 541,"dimension": 1},{"entity_id": 144115188076142326,"chunk_index": 5147,"x": 14062,"z": 544,"dimension": 1},{"entity_id": 144115188076142300,"chunk_index": 5146,"x": 13988,"z": 544,"dimension": 1},{"entity_id": 144115188076142430,"chunk_index": 5147,"x": 14036,"z": 547,"dimension": 1},{"entity_id": 144115188076142465,"chunk_index": 5147,"x": 14073,"z": 547,"dimension": 1},{"entity_id": 144115188076142481,"chunk_index": 5147,"x": 14099,"z": 547,"dimension": 1},{"entity_id": 144115188076142590,"chunk_index": 5147,"x": 14079,"z": 550,"dimension": 1},{"entity_id": 144115188076142537,"chunk_index": 5146,"x": 13982,"z": 550,"dimension": 1},{"entity_id": 144115188076142608,"chunk_index": 5145,"x": 13844,"z": 553,"dimension": 1},{"entity_id": 144115188076142646,"chunk_index": 5146,"x": 14001,"z": 553,"dimension": 1},{"entity_id": 144115188076142644,"chunk_index": 5146,"x": 13989,"z": 553,"dimension": 1},{"entity_id": 144115188076142919,"chunk_index": 5147,"x": 14063,"z": 559,"dimension": 1},{"entity_id": 144115188076142688,"chunk_index": 5147,"x": 14073,"z": 553,"dimension": 1},{"entity_id": 144115188076142830,"chunk_index": 5145,"x": 13851,"z": 559,"dimension": 1},{"entity_id": 144115188076142929,"chunk_index": 5147,"x": 14088,"z": 559,"dimension": 1},{"entity_id": 144115188076142949,"chunk_index": 5145,"x": 13869,"z": 562,"dimension": 1},{"entity_id": 144115188076143005,"chunk_index": 5147,"x": 14074,"z": 562,"dimension": 1},{"entity_id": 144115188076143009,"chunk_index": 5145,"x": 13844,"z": 565,"dimension": 1},{"entity_id": 144115188076143019,"chunk_index": 5145,"x": 13902,"z": 565,"dimension": 1},{"entity_id": 144115188076143194,"chunk_index": 5145,"x": 13850,"z": 571,"dimension": 1},{"entity_id": 144115188076143070,"chunk_index": 5147,"x": 14048,"z": 565,"dimension": 1},{"entity_id": 144115188076143324,"chunk_index": 5145,"x": 13850,"z": 574,"dimension": 1},{"entity_id": 144115188076143326,"chunk_index": 5145,"x": 13851,"z": 574,"dimension": 1},{"entity_id": 144115188076143340,"chunk_index": 5145,"x": 13874,"z": 574,"dimension": 1}]